{
  "0": "Unavailable",
  "1": "Unavailable",
  "2": "Modificação de Grande Jagras",
  "3": "Aumenta um pouco o poder de ataque.\r\n<STYL MOJI_YELLOW_DEFAULT>(Melhoria nível 1)</STYL>",
  "4": "Modificação de Pukei-Pukei",
  "5": "Aumenta um pouco o dano elemental e\r\nde status anormal.\r\n<STYL MOJI_YELLOW_DEFAULT>(Melhoria nível 1)</STYL>",
  "6": "Modificação de Barroth",
  "7": "Acrescenta defesa ao seu equipamento.\r\n<STYL MOJI_YELLOW_DEFAULT>(Melhoria nível 1)</STYL>",
  "8": "Modificação de Grande Girros",
  "9": "Aumenta um pouco a afinidade.\r\n<STYL MOJI_YELLOW_DEFAULT>(Melhoria nível 1)</STYL>",
  "10": "Modificação de Beotodus",
  "11": "Acrescenta defesa ao seu equipamento.\r\n<STYL MOJI_YELLOW_DEFAULT>(Melhoria nível 2)</STYL>",
  "12": "Modificação de Banbaro",
  "13": "Aumenta um pouco o poder de ataque.\r\n<STYL MOJI_YELLOW_DEFAULT>(Melhoria nível 2)</STYL>",
  "14": "Modificação Paolumu Beladona",
  "15": "Aumenta um pouco a afinidade.\r\n<STYL MOJI_YELLOW_DEFAULT>(Melhoria nível 2)</STYL>",
  "16": "Modificação Pukei Coralino",
  "17": "Aumenta um pouco o dano elemental e\r\nde status anormal.\r\n<STYL MOJI_YELLOW_DEFAULT>(Melhoria nível 2)</STYL>",
  "18": "Modificação de Radobaan",
  "19": "Aumenta um pouco o poder de ataque.\r\n<STYL MOJI_YELLOW_DEFAULT>(Melhoria nível 3)</STYL>",
  "20": "Modificação de Lavasioth",
  "21": "Aumenta um pouco o dano elemental e\r\nde status anormal.\r\n<STYL MOJI_YELLOW_DEFAULT>(Melhoria nível 3)</STYL>",
  "22": "Modificação de Nargacuga",
  "23": "Aumenta um pouco a afinidade.\r\n<STYL MOJI_YELLOW_DEFAULT>(Melhoria nível 3)</STYL>",
  "24": "Modificação de Glavenus",
  "25": "Aumenta um pouco o dano elemental e\r\nde status anormal.\r\n<STYL MOJI_YELLOW_DEFAULT>(Melhoria nível 4)</STYL>",
  "26": "Modificação de Rathalos",
  "27": "Aumenta um pouco a afinidade.\r\n<STYL MOJI_YELLOW_DEFAULT>(Melhoria nível 4)</STYL>",
  "28": "Modificação Glavenus Ácido",
  "29": "Aumenta um pouco o poder de ataque.\r\n<STYL MOJI_YELLOW_DEFAULT>(Melhoria nível 4)</STYL>",
  "30": "Modificação de Zinogre",
  "31": "Aumenta um pouco o dano elemental e\r\nde status anormal.\r\n<STYL MOJI_YELLOW_DEFAULT>(Melhoria nível 5)</STYL>",
  "32": "Modificação de Vaal Hazak",
  "33": "Aumenta um pouco a afinidade.\r\n<STYL MOJI_YELLOW_DEFAULT>(Melhoria nível 5)</STYL>",
  "34": "Modificação de Nergigante",
  "35": "Aumenta um pouco o poder de ataque.\r\n<STYL MOJI_YELLOW_DEFAULT>(Melhoria nível 5)</STYL>",
  "36": "Modificação Zorah Magdaros",
  "37": "Aumenta um pouco o dano de ataque.\r\n<STYL MOJI_YELLOW_DEFAULT>(Melhoria nível 6)</STYL>",
  "38": "Modificação de Nergigante+",
  "39": "Aumenta razoavelmente o poder de ataque.\r\n<STYL MOJI_YELLOW_DEFAULT>(Melhoria nível 7)</STYL>",
  "40": "Mod. de Zinogre Tenebroso",
  "41": "Aumenta razoavelmente a afinidade.\r\n<STYL MOJI_YELLOW_DEFAULT>(Melhoria nível 7)</STYL>",
  "42": "Modificação de Xeno'jiiva",
  "43": "Aumenta um pouco a afiação.\r\n<STYL MOJI_YELLOW_DEFAULT>(Melhoria nível 7)</STYL>",
  "44": "Unavailable",
  "45": "Unavailable",
  "46": "Unavailable",
  "47": "Unavailable",
  "48": "Unavailable",
  "49": "Unavailable",
  "50": "Unavailable",
  "51": "Unavailable",
  "52": "Unavailable",
  "53": "Unavailable",
  "54": "Unavailable",
  "55": "Unavailable",
  "56": "Unavailable",
  "57": "Unavailable",
  "58": "Unavailable",
  "59": "Unavailable",
  "60": "Unavailable",
  "61": "Unavailable",
  "62": "Unavailable",
  "63": "Unavailable",
  "64": "Unavailable",
  "65": "Unavailable",
  "66": "Unavailable",
  "67": "Unavailable",
  "68": "Unavailable",
  "69": "Unavailable",
  "70": "Unavailable",
  "71": "Unavailable",
  "72": "Unavailable",
  "73": "Unavailable",
  "74": "Unavailable",
  "75": "Unavailable",
  "76": "Unavailable",
  "77": "Unavailable",
  "78": "Unavailable",
  "79": "Unavailable",
  "80": "Modificação de Grande Jagras",
  "81": "Aumenta um pouco o poder de ataque.\r\n<STYL MOJI_YELLOW_DEFAULT>(Melhoria nível 1)</STYL>",
  "82": "Modificação de Barroth",
  "83": "Aumenta um pouco o dano elemental e\r\nde status anormal.\r\n<STYL MOJI_YELLOW_DEFAULT>(Melhoria nível 1)</STYL>",
  "84": "Modificação de Grande Girros",
  "85": "Aumenta um pouco a afinidade.\r\n<STYL MOJI_YELLOW_DEFAULT>(Melhoria nível 1)</STYL>",
  "86": "Modificação de Pukei-Pukei",
  "87": "Aumenta um pouco o dano elemental e\r\nde status anormal.\r\n<STYL MOJI_YELLOW_DEFAULT>(Melhoria nível 2)</STYL>",
  "88": "Modificação de Anjanath",
  "89": "Aumenta um pouco o poder de ataque.\r\n<STYL MOJI_YELLOW_DEFAULT>(Melhoria nível 2)</STYL>",
  "90": "Modificação de Paolumu",
  "91": "Aumenta um pouco a afinidade.\r\n<STYL MOJI_YELLOW_DEFAULT>(Melhoria nível 2)</STYL>",
  "92": "Modificação de Radobaan",
  "93": "Aumenta um pouco o poder de ataque.\r\n<STYL MOJI_YELLOW_DEFAULT>(Melhoria nível 3)</STYL>",
  "94": "Modificação Paolumu Beladona",
  "95": "Aumenta um pouco a afinidade.\r\n<STYL MOJI_YELLOW_DEFAULT>(Melhoria nível 3)</STYL>",
  "96": "Modificação Pukei Coralino",
  "97": "Aumenta um pouco o dano elemental e\r\nde status anormal.\r\n<STYL MOJI_YELLOW_DEFAULT>(Melhoria nível 3)</STYL>",
  "98": "Modificação de Legiana",
  "99": "Aumenta um pouco o dano elemental e\r\nde status anormal.\r\n<STYL MOJI_YELLOW_DEFAULT>(Melhoria nível 4)</STYL>",
  "100": "Modificação de Rathalos",
  "101": "Aumenta um pouco a afinidade.\r\n<STYL MOJI_YELLOW_DEFAULT>(Melhoria nível 4)</STYL>",
  "102": "Modificação de Glavenus",
  "103": "Aumenta um pouco o poder de ataque.\r\n<STYL MOJI_YELLOW_DEFAULT>(Melhoria nível 4)</STYL>",
  "104": "Modificação Glavenus Ácido",
  "105": "Aumenta um pouco a afinidade.\r\n<STYL MOJI_YELLOW_DEFAULT>(Melhoria nível 5)</STYL>",
  "106": "Modificação de Kirin",
  "107": "Aumenta um pouco o dano elemental e\r\nde status anormal.\r\n<STYL MOJI_YELLOW_DEFAULT>(Melhoria nível 5)</STYL>",
  "108": "Modificação de Nergigante",
  "109": "Aumenta um pouco o poder de ataque.\r\n<STYL MOJI_YELLOW_DEFAULT>(Melhoria nível 5)</STYL>",
  "110": "Modificação de Namielle",
  "111": "Aumenta um pouco o dano de ataque.\r\n<STYL MOJI_YELLOW_DEFAULT>(Melhoria nível 6)</STYL>",
  "112": "Modificação de Nergigante+",
  "113": "Aumenta razoavelmente o poder de ataque.\r\n<STYL MOJI_YELLOW_DEFAULT>(Melhoria nível 7)</STYL>",
  "114": "Modificação de Barioth",
  "115": "Aumenta razoavelmente a afinidade.\r\n<STYL MOJI_YELLOW_DEFAULT>(Melhoria nível 7)</STYL>",
  "116": "Modificação de Xeno'jiiva",
  "117": "Aumenta um pouco a afiação.\r\n<STYL MOJI_YELLOW_DEFAULT>(Melhoria nível 7)</STYL>",
  "118": "Unavailable",
  "119": "Unavailable",
  "120": "Unavailable",
  "121": "Unavailable",
  "122": "Unavailable",
  "123": "Unavailable",
  "124": "Unavailable",
  "125": "Unavailable",
  "126": "Unavailable",
  "127": "Unavailable",
  "128": "Unavailable",
  "129": "Unavailable",
  "130": "Unavailable",
  "131": "Unavailable",
  "132": "Unavailable",
  "133": "Unavailable",
  "134": "Unavailable",
  "135": "Unavailable",
  "136": "Unavailable",
  "137": "Unavailable",
  "138": "Unavailable",
  "139": "Unavailable",
  "140": "Unavailable",
  "141": "Unavailable",
  "142": "Unavailable",
  "143": "Unavailable",
  "144": "Unavailable",
  "145": "Unavailable",
  "146": "Unavailable",
  "147": "Unavailable",
  "148": "Unavailable",
  "149": "Unavailable",
  "150": "Unavailable",
  "151": "Unavailable",
  "152": "Unavailable",
  "153": "Unavailable",
  "154": "Unavailable",
  "155": "Unavailable",
  "156": "Unavailable",
  "157": "Unavailable",
  "158": "Modificação de Kulu-Ya-Ku",
  "159": "Aumenta um pouco a afinidade.\r\n<STYL MOJI_YELLOW_DEFAULT>(Melhoria nível 1)</STYL>",
  "160": "Modificação de Jyuratodus",
  "161": "Aumenta um pouco o dano elemental e\r\nde status anormal.\r\n<STYL MOJI_YELLOW_DEFAULT>(Melhoria nível 1)</STYL>",
  "162": "Modificação de Tzitzi-Ya-Ku",
  "163": "Aumenta um pouco o poder de ataque.\r\n<STYL MOJI_YELLOW_DEFAULT>(Melhoria nível 1)</STYL>",
  "164": "Modificação de Chifrotauro",
  "165": "Acrescenta defesa ao seu equipamento.\r\n<STYL MOJI_YELLOW_DEFAULT>(Melhoria nível 1)</STYL>",
  "166": "Modificação de Tobi-Kadachi",
  "167": "Aumenta um pouco a afinidade.\r\n<STYL MOJI_YELLOW_DEFAULT>(Melhoria nível 2)</STYL>",
  "168": "Modificação de Beotodus",
  "169": "Acrescenta defesa ao seu equipamento.\r\n<STYL MOJI_YELLOW_DEFAULT>(Melhoria nível 2)</STYL>",
  "170": "Modificação de Banbaro",
  "171": "Aumenta um pouco o poder de ataque.\r\n<STYL MOJI_YELLOW_DEFAULT>(Melhoria nível 2)</STYL>",
  "172": "Modificação de Anjanath",
  "173": "Aumenta um pouco o dano elemental e\r\nde status anormal.\r\n<STYL MOJI_YELLOW_DEFAULT>(Melhoria nível 2)</STYL>",
  "174": "Modificação Kadachi Vípero",
  "175": "Aumenta um pouco o dano elemental e\r\nde status anormal.\r\n<STYL MOJI_YELLOW_DEFAULT>(Melhoria nível 3)</STYL>",
  "176": "Modificação de Odogaron",
  "177": "Aumenta um pouco a afinidade.\r\n<STYL MOJI_YELLOW_DEFAULT>(Melhoria nível 3)</STYL>",
  "178": "Modificação de Diablos",
  "179": "Aumenta um pouco o poder de ataque.\r\n<STYL MOJI_YELLOW_DEFAULT>(Melhoria nível 3)</STYL>",
  "180": "Modificação de Lavasioth",
  "181": "Acrescenta defesa ao seu equipamento.\r\n<STYL MOJI_YELLOW_DEFAULT>(Melhoria nível 3)</STYL>",
  "182": "Modificação de Nargacuga",
  "183": "Aumenta um pouco a afinidade.\r\n<STYL MOJI_YELLOW_DEFAULT>(Melhoria nível 4)</STYL>",
  "184": "Modificação de Tigrex",
  "185": "Aumenta um pouco o poder de ataque.\r\n<STYL MOJI_YELLOW_DEFAULT>(Melhoria nível 4)</STYL>",
  "186": "Mod. de Anjanath Fulgurante",
  "187": "Aumenta um pouco o dano elemental e\r\nde status anormal.\r\n<STYL MOJI_YELLOW_DEFAULT>(Melhoria nível 4)</STYL>",
  "188": "Modificação de Diablos Negra",
  "189": "Acrescenta defesa ao seu equipamento.\r\n<STYL MOJI_YELLOW_DEFAULT>(Melhoria nível 4)</STYL>",
  "190": "Modificação de Tigrex Bruto",
  "191": "Aumenta um pouco a afinidade.\r\n<STYL MOJI_YELLOW_DEFAULT>(Melhoria nível 5)</STYL>",
  "192": "Modificação Zorah Magdaros",
  "193": "Aumenta um pouco o dano elemental e\r\nde status anormal.\r\n<STYL MOJI_YELLOW_DEFAULT>(Melhoria nível 5)</STYL>",
  "194": "Modificação de Nergigante",
  "195": "Aumenta um pouco o poder de ataque.\r\n<STYL MOJI_YELLOW_DEFAULT>(Melhoria nível 5)</STYL>",
  "196": "Modificação de Brachydios",
  "197": "Aumenta um pouco o dano de ataque.\r\n<STYL MOJI_YELLOW_DEFAULT>(Melhoria nível 6)</STYL>",
  "198": "Modificação de Nergigante+",
  "199": "Aumenta razoavelmente o poder de ataque.\r\n<STYL MOJI_YELLOW_DEFAULT>(Melhoria nível 7)</STYL>",
  "200": "Mod. de Zinogre Tenebroso",
  "201": "Aumenta razoavelmente a afinidade.\r\n<STYL MOJI_YELLOW_DEFAULT>(Melhoria nível 7)</STYL>",
  "202": "Modificação de Xeno'jiiva",
  "203": "Aumenta um pouco a afiação.\r\n<STYL MOJI_YELLOW_DEFAULT>(Melhoria nível 7)</STYL>",
  "204": "Unavailable",
  "205": "Unavailable",
  "206": "Unavailable",
  "207": "Unavailable",
  "208": "Unavailable",
  "209": "Unavailable",
  "210": "Unavailable",
  "211": "Unavailable",
  "212": "Unavailable",
  "213": "Unavailable",
  "214": "Unavailable",
  "215": "Unavailable",
  "216": "Unavailable",
  "217": "Unavailable",
  "218": "Unavailable",
  "219": "Unavailable",
  "220": "Unavailable",
  "221": "Unavailable",
  "222": "Unavailable",
  "223": "Unavailable",
  "224": "Unavailable",
  "225": "Unavailable",
  "226": "Unavailable",
  "227": "Unavailable",
  "228": "Unavailable",
  "229": "Unavailable",
  "230": "Unavailable",
  "231": "Unavailable",
  "232": "Unavailable",
  "233": "Unavailable",
  "234": "Unavailable",
  "235": "Unavailable",
  "236": "Modificação de Kulu-Ya-Ku",
  "237": "Aumenta um pouco a afinidade.\r\n<STYL MOJI_YELLOW_DEFAULT>(Melhoria nível 1)</STYL>",
  "238": "Modificação de Jyuratodus",
  "239": "Aumenta um pouco o dano elemental e\r\nde status anormal.\r\n<STYL MOJI_YELLOW_DEFAULT>(Melhoria nível 1)</STYL>",
  "240": "Modificação de Tzitzi-Ya-Ku",
  "241": "Aumenta um pouco o poder de ataque.\r\n<STYL MOJI_YELLOW_DEFAULT>(Melhoria nível 1)</STYL>",
  "242": "Modificação de Banbaro",
  "243": "Aumenta um pouco o poder de ataque.\r\n<STYL MOJI_YELLOW_DEFAULT>(Melhoria nível 2)</STYL>",
  "244": "Modificação de Tobi-Kadachi",
  "245": "Aumenta um pouco o dano elemental e\r\nde status anormal.\r\n<STYL MOJI_YELLOW_DEFAULT>(Melhoria nível 2)</STYL>",
  "246": "Modificação de Chifrotauro",
  "247": "Aumenta um pouco a afinidade.\r\n<STYL MOJI_YELLOW_DEFAULT>(Melhoria nível 2)</STYL>",
  "248": "Modificação de Anjanath",
  "249": "Aumenta um pouco o poder de ataque.\r\n<STYL MOJI_YELLOW_DEFAULT>(Melhoria nível 3)</STYL>",
  "250": "Modificação Kadachi Vípero",
  "251": "Aumenta um pouco a afinidade.\r\n<STYL MOJI_YELLOW_DEFAULT>(Melhoria nível 3)</STYL>",
  "252": "Modificação de Legiana",
  "253": "Aumenta um pouco o dano elemental e\r\nde status anormal.\r\n<STYL MOJI_YELLOW_DEFAULT>(Melhoria nível 3)</STYL>",
  "254": "Modificação de Glavenus",
  "255": "Aumenta um pouco o dano elemental e\r\nde status anormal.\r\n<STYL MOJI_YELLOW_DEFAULT>(Melhoria nível 4)</STYL>",
  "256": "Mod. de Anjanath Fulgurante",
  "257": "Aumenta um pouco a afinidade.\r\n<STYL MOJI_YELLOW_DEFAULT>(Melhoria nível 4)</STYL>",
  "258": "Modificação Glavenus Ácido",
  "259": "Aumenta um pouco o poder de ataque.\r\n<STYL MOJI_YELLOW_DEFAULT>(Melhoria nível 4)</STYL>",
  "260": "Modificação Zorah Magdaros",
  "261": "Aumenta um pouco o dano elemental e\r\nde status anormal.\r\n<STYL MOJI_YELLOW_DEFAULT>(Melhoria nível 5)</STYL>",
  "262": "Modificação de Vaal Hazak",
  "263": "Aumenta um pouco a afinidade.\r\n<STYL MOJI_YELLOW_DEFAULT>(Melhoria nível 5)</STYL>",
  "264": "Modificação de Nergigante",
  "265": "Aumenta um pouco o poder de ataque.\r\n<STYL MOJI_YELLOW_DEFAULT>(Melhoria nível 5)</STYL>",
  "266": "Modificação de Brachydios",
  "267": "Aumenta um pouco o dano de ataque.\r\n<STYL MOJI_YELLOW_DEFAULT>(Melhoria nível 6)</STYL>",
  "268": "Modificação de Uragaan",
  "269": "Aumenta um pouco o dano elemental e\r\nde status anormal.\r\n<STYL MOJI_YELLOW_DEFAULT>(Melhoria nível 6)</STYL>",
  "270": "Modificação de Vaal Hazak+",
  "271": "Aumenta um pouco a afinidade.\r\n<STYL MOJI_YELLOW_DEFAULT>(Melhoria nível 6)</STYL>",
  "272": "Modificação de Nergigante+",
  "273": "Aumenta razoavelmente o poder de ataque.\r\n<STYL MOJI_YELLOW_DEFAULT>(Melhoria nível 7)</STYL>",
  "274": "Modificação de Barioth",
  "275": "Aumenta razoavelmente a afinidade.\r\n<STYL MOJI_YELLOW_DEFAULT>(Melhoria nível 7)</STYL>",
  "276": "Modificação de Xeno'jiiva",
  "277": "Aumenta um pouco a afiação.\r\n<STYL MOJI_YELLOW_DEFAULT>(Melhoria nível 7)</STYL>",
  "278": "Unavailable",
  "279": "Unavailable",
  "280": "Unavailable",
  "281": "Unavailable",
  "282": "Unavailable",
  "283": "Unavailable",
  "284": "Unavailable",
  "285": "Unavailable",
  "286": "Unavailable",
  "287": "Unavailable",
  "288": "Unavailable",
  "289": "Unavailable",
  "290": "Unavailable",
  "291": "Unavailable",
  "292": "Unavailable",
  "293": "Unavailable",
  "294": "Unavailable",
  "295": "Unavailable",
  "296": "Unavailable",
  "297": "Unavailable",
  "298": "Unavailable",
  "299": "Unavailable",
  "300": "Unavailable",
  "301": "Unavailable",
  "302": "Unavailable",
  "303": "Unavailable",
  "304": "Unavailable",
  "305": "Unavailable",
  "306": "Unavailable",
  "307": "Unavailable",
  "308": "Unavailable",
  "309": "Unavailable",
  "310": "Unavailable",
  "311": "Unavailable",
  "312": "Unavailable",
  "313": "Unavailable",
  "314": "Modificação de Kulu-Ya-Ku",
  "315": "Aumenta um pouco a afinidade.\r\n<STYL MOJI_YELLOW_DEFAULT>(Melhoria nível 1)</STYL>",
  "316": "Modificação de Pukei-Pukei",
  "317": "Aumenta um pouco o dano elemental e\r\nde status anormal.\r\n<STYL MOJI_YELLOW_DEFAULT>(Melhoria nível 1)</STYL>",
  "318": "Modificação de Grande Girros",
  "319": "Aumenta um pouco o poder de ataque.\r\n<STYL MOJI_YELLOW_DEFAULT>(Melhoria nível 1)</STYL>",
  "320": "Modificação de Barroth",
  "321": "Aumenta um pouco o poder de ataque.\r\n<STYL MOJI_YELLOW_DEFAULT>(Melhoria nível 2)</STYL>",
  "322": "Modificação de Banbaro",
  "323": "Aumenta um pouco a afinidade.\r\n<STYL MOJI_YELLOW_DEFAULT>(Melhoria nível 2)</STYL>",
  "324": "Modificação de Radobaan",
  "325": "Aumenta um pouco o dano elemental e\r\nde status anormal.\r\n<STYL MOJI_YELLOW_DEFAULT>(Melhoria nível 2)</STYL>",
  "326": "Modificação de Anjanath",
  "327": "Aumenta um pouco o dano elemental e\r\nde status anormal.\r\n<STYL MOJI_YELLOW_DEFAULT>(Melhoria nível 3)</STYL>",
  "328": "Modificação Paolumu Beladona",
  "329": "Aumenta um pouco a afinidade.\r\n<STYL MOJI_YELLOW_DEFAULT>(Melhoria nível 3)</STYL>",
  "330": "Modificação de Diablos",
  "331": "Aumenta um pouco o poder de ataque.\r\n<STYL MOJI_YELLOW_DEFAULT>(Melhoria nível 3)</STYL>",
  "332": "Modificação de Tigrex",
  "333": "Aumenta um pouco o poder de ataque.\r\n<STYL MOJI_YELLOW_DEFAULT>(Melhoria nível 4)</STYL>",
  "334": "Mod. de Anjanath Fulgurante",
  "335": "Aumenta um pouco o dano elemental e\r\nde status anormal.\r\n<STYL MOJI_YELLOW_DEFAULT>(Melhoria nível 4)</STYL>",
  "336": "Modificação de Diablos Negra",
  "337": "Acrescenta defesa ao seu equipamento.\r\n<STYL MOJI_YELLOW_DEFAULT>(Melhoria nível 4)</STYL>",
  "338": "Modificação de Yian Garuga",
  "339": "Aumenta um pouco a afinidade.\r\n<STYL MOJI_YELLOW_DEFAULT>(Melhoria nível 4)</STYL>",
  "340": "Modificação de Tigrex Bruto",
  "341": "Aumenta um pouco a afinidade.\r\n<STYL MOJI_YELLOW_DEFAULT>(Melhoria nível 5)</STYL>",
  "342": "Modificação de Vaal Hazak",
  "343": "Aumenta um pouco o dano elemental e\r\nde status anormal.\r\n<STYL MOJI_YELLOW_DEFAULT>(Melhoria nível 5)</STYL>",
  "344": "Modificação de Nergigante",
  "345": "Aumenta um pouco o poder de ataque.\r\n<STYL MOJI_YELLOW_DEFAULT>(Melhoria nível 5)</STYL>",
  "346": "Modificação de Uragaan",
  "347": "Aumenta um pouco o dano de ataque.\r\n<STYL MOJI_YELLOW_DEFAULT>(Melhoria nível 6)</STYL>",
  "348": "Modificação de Nergigante+",
  "349": "Aumenta razoavelmente o poder de ataque.\r\n<STYL MOJI_YELLOW_DEFAULT>(Melhoria nível 7)</STYL>",
  "350": "Modificação de Barioth",
  "351": "Aumenta razoavelmente a afinidade.\r\n<STYL MOJI_YELLOW_DEFAULT>(Melhoria nível 7)</STYL>",
  "352": "Modificação de Xeno'jiiva",
  "353": "Aumenta um pouco a afiação.\r\n<STYL MOJI_YELLOW_DEFAULT>(Melhoria nível 7)</STYL>",
  "354": "Unavailable",
  "355": "Unavailable",
  "356": "Unavailable",
  "357": "Unavailable",
  "358": "Unavailable",
  "359": "Unavailable",
  "360": "Unavailable",
  "361": "Unavailable",
  "362": "Unavailable",
  "363": "Unavailable",
  "364": "Unavailable",
  "365": "Unavailable",
  "366": "Unavailable",
  "367": "Unavailable",
  "368": "Unavailable",
  "369": "Unavailable",
  "370": "Unavailable",
  "371": "Unavailable",
  "372": "Unavailable",
  "373": "Unavailable",
  "374": "Unavailable",
  "375": "Unavailable",
  "376": "Unavailable",
  "377": "Unavailable",
  "378": "Unavailable",
  "379": "Unavailable",
  "380": "Unavailable",
  "381": "Unavailable",
  "382": "Unavailable",
  "383": "Unavailable",
  "384": "Unavailable",
  "385": "Unavailable",
  "386": "Unavailable",
  "387": "Unavailable",
  "388": "Unavailable",
  "389": "Unavailable",
  "390": "Unavailable",
  "391": "Unavailable",
  "392": "Modificação de Kulu-Ya-Ku",
  "393": "Aumenta um pouco a afinidade.\r\n<STYL MOJI_YELLOW_DEFAULT>(Melhoria nível 1)</STYL>",
  "394": "Modificação de Pukei-Pukei",
  "395": "Aumenta um pouco o dano elemental e\r\nde status anormal.\r\n<STYL MOJI_YELLOW_DEFAULT>(Melhoria nível 1)</STYL>",
  "396": "Modificação de Dodogama",
  "397": "Aumenta um pouco o poder de ataque.\r\n<STYL MOJI_YELLOW_DEFAULT>(Melhoria nível 1)</STYL>",
  "398": "Modificação de Paolumu",
  "399": "Aumenta um pouco a afinidade.\r\n<STYL MOJI_YELLOW_DEFAULT>(Melhoria nível 2)</STYL>",
  "400": "Modificação de Radobaan",
  "401": "Aumenta um pouco o poder de ataque.\r\n<STYL MOJI_YELLOW_DEFAULT>(Melhoria nível 2)</STYL>",
  "402": "Modificação de Vespoidea",
  "403": "Aumenta um pouco o dano elemental e\r\nde status anormal.\r\n<STYL MOJI_YELLOW_DEFAULT>(Melhoria nível 2)</STYL>",
  "404": "Modificação de Anjanath",
  "405": "Aumenta um pouco o poder de ataque.\r\n<STYL MOJI_YELLOW_DEFAULT>(Melhoria nível 3)</STYL>",
  "406": "Modificação Paolumu Beladona",
  "407": "Aumenta um pouco a afinidade.\r\n<STYL MOJI_YELLOW_DEFAULT>(Melhoria nível 3)</STYL>",
  "408": "Modificação Pukei Coralino",
  "409": "Aumenta um pouco o dano elemental e\r\nde status anormal.\r\n<STYL MOJI_YELLOW_DEFAULT>(Melhoria nível 3)</STYL>",
  "410": "Modificação de Legiana",
  "411": "Aumenta um pouco o dano elemental e\r\nde status anormal.\r\n<STYL MOJI_YELLOW_DEFAULT>(Melhoria nível 4)</STYL>",
  "412": "Mod. de Anjanath Fulgurante",
  "413": "Aumenta um pouco a afinidade.\r\n<STYL MOJI_YELLOW_DEFAULT>(Melhoria nível 4)</STYL>",
  "414": "Modificação de Bazelgeuse",
  "415": "Aumenta um pouco o poder de ataque.\r\n<STYL MOJI_YELLOW_DEFAULT>(Melhoria nível 4)</STYL>",
  "416": "Modificação de Kirin",
  "417": "Aumenta um pouco o dano elemental e\r\nde status anormal.\r\n<STYL MOJI_YELLOW_DEFAULT>(Melhoria nível 5)</STYL>",
  "418": "Modificação de Namielle",
  "419": "Aumenta um pouco a afinidade.\r\n<STYL MOJI_YELLOW_DEFAULT>(Melhoria nível 5)</STYL>",
  "420": "Modificação de Nergigante",
  "421": "Aumenta um pouco o poder de ataque.\r\n<STYL MOJI_YELLOW_DEFAULT>(Melhoria nível 5)</STYL>",
  "422": "Modificação de Brachydios",
  "423": "Aumenta um pouco o dano de ataque.\r\n<STYL MOJI_YELLOW_DEFAULT>(Melhoria nível 6)</STYL>",
  "424": "Modificação de Nergigante+",
  "425": "Aumenta razoavelmente o poder de ataque.\r\n<STYL MOJI_YELLOW_DEFAULT>(Melhoria nível 7)</STYL>",
  "426": "Modificação de Barioth",
  "427": "Aumenta razoavelmente a afinidade.\r\n<STYL MOJI_YELLOW_DEFAULT>(Melhoria nível 7)</STYL>",
  "428": "Modificação de Xeno'jiiva",
  "429": "Aumenta um pouco a afiação.\r\n<STYL MOJI_YELLOW_DEFAULT>(Melhoria nível 7)</STYL>",
  "430": "Unavailable",
  "431": "Unavailable",
  "432": "Unavailable",
  "433": "Unavailable",
  "434": "Unavailable",
  "435": "Unavailable",
  "436": "Unavailable",
  "437": "Unavailable",
  "438": "Unavailable",
  "439": "Unavailable",
  "440": "Unavailable",
  "441": "Unavailable",
  "442": "Unavailable",
  "443": "Unavailable",
  "444": "Unavailable",
  "445": "Unavailable",
  "446": "Unavailable",
  "447": "Unavailable",
  "448": "Unavailable",
  "449": "Unavailable",
  "450": "Unavailable",
  "451": "Unavailable",
  "452": "Unavailable",
  "453": "Unavailable",
  "454": "Unavailable",
  "455": "Unavailable",
  "456": "Unavailable",
  "457": "Unavailable",
  "458": "Unavailable",
  "459": "Unavailable",
  "460": "Unavailable",
  "461": "Unavailable",
  "462": "Unavailable",
  "463": "Unavailable",
  "464": "Unavailable",
  "465": "Unavailable",
  "466": "Unavailable",
  "467": "Unavailable",
  "468": "Unavailable",
  "469": "Unavailable",
  "470": "Modificação de Kulu-Ya-Ku",
  "471": "Aumenta um pouco a afinidade.\r\n<STYL MOJI_YELLOW_DEFAULT>(Melhoria nível 1)</STYL>",
  "472": "Modificação de Pukei-Pukei",
  "473": "Aumenta um pouco o dano elemental e\r\nde status anormal.\r\n<STYL MOJI_YELLOW_DEFAULT>(Melhoria nível 1)</STYL>",
  "474": "Modificação de Barroth",
  "475": "Aumenta um pouco o poder de ataque.\r\n<STYL MOJI_YELLOW_DEFAULT>(Melhoria nível 1)</STYL>",
  "476": "Modificação de Dodogama",
  "477": "Aumenta um pouco o poder de ataque.\r\n<STYL MOJI_YELLOW_DEFAULT>(Melhoria nível 2)</STYL>",
  "478": "Modificação Paolumu Beladona",
  "479": "Aumenta um pouco a afinidade.\r\n<STYL MOJI_YELLOW_DEFAULT>(Melhoria nível 2)</STYL>",
  "480": "Modificação Pukei Coralino",
  "481": "Aumenta um pouco o dano elemental e\r\nde status anormal.\r\n<STYL MOJI_YELLOW_DEFAULT>(Melhoria nível 2)</STYL>",
  "482": "Modificação de Chifrotauro",
  "483": "Acrescenta defesa ao seu equipamento.\r\n<STYL MOJI_YELLOW_DEFAULT>(Melhoria nível 2)</STYL>",
  "484": "Modificação de Legiana",
  "485": "Aumenta um pouco o dano elemental e\r\nde status anormal.\r\n<STYL MOJI_YELLOW_DEFAULT>(Melhoria nível 3)</STYL>",
  "486": "Modificação de Odogaron",
  "487": "Aumenta um pouco o poder de ataque.\r\n<STYL MOJI_YELLOW_DEFAULT>(Melhoria nível 3)</STYL>",
  "488": "Modificação de Nargacuga",
  "489": "Aumenta um pouco a afinidade.\r\n<STYL MOJI_YELLOW_DEFAULT>(Melhoria nível 3)</STYL>",
  "490": "Modificação de Rathalos",
  "491": "Aumenta um pouco o poder de ataque.\r\n<STYL MOJI_YELLOW_DEFAULT>(Melhoria nível 4)</STYL>",
  "492": "Modificação Odogaron Negro",
  "493": "Aumenta um pouco a afinidade.\r\n<STYL MOJI_YELLOW_DEFAULT>(Melhoria nível 4)</STYL>",
  "494": "Modificação de Zinogre",
  "495": "Aumenta um pouco o dano elemental e\r\nde status anormal.\r\n<STYL MOJI_YELLOW_DEFAULT>(Melhoria nível 4)</STYL>",
  "496": "Modificação de Namielle",
  "497": "Aumenta um pouco a afinidade.\r\n<STYL MOJI_YELLOW_DEFAULT>(Melhoria nível 5)</STYL>",
  "498": "Modificação de Vaal Hazak",
  "499": "Aumenta um pouco o dano elemental e\r\nde status anormal.\r\n<STYL MOJI_YELLOW_DEFAULT>(Melhoria nível 5)</STYL>",
  "500": "Modificação de Nergigante",
  "501": "Aumenta um pouco o poder de ataque.\r\n<STYL MOJI_YELLOW_DEFAULT>(Melhoria nível 5)</STYL>",
  "502": "Modificação de Brachydios",
  "503": "Aumenta um pouco o dano de ataque.\r\n<STYL MOJI_YELLOW_DEFAULT>(Melhoria nível 6)</STYL>",
  "504": "Modificação de Nergigante+",
  "505": "Aumenta razoavelmente o poder de ataque.\r\n<STYL MOJI_YELLOW_DEFAULT>(Melhoria nível 7)</STYL>",
  "506": "Modificação de Legiana+",
  "507": "Acrescenta defesa ao seu equipamento.\r\n<STYL MOJI_YELLOW_DEFAULT>(Melhoria nível 7)</STYL>",
  "508": "Modificação de Barioth",
  "509": "Aumenta razoavelmente a afinidade.\r\n<STYL MOJI_YELLOW_DEFAULT>(Melhoria nível 7)</STYL>",
  "510": "Mod. de Zinogre Tenebroso",
  "511": "Aumenta um pouco o dano elemental e\r\nde status anormal.\r\n<STYL MOJI_YELLOW_DEFAULT>(Melhoria nível 7)</STYL>",
  "512": "Modificação de Xeno'jiiva",
  "513": "Aumenta um pouco a afiação.\r\n<STYL MOJI_YELLOW_DEFAULT>(Melhoria nível 7)</STYL>",
  "514": "Unavailable",
  "515": "Unavailable",
  "516": "Unavailable",
  "517": "Unavailable",
  "518": "Unavailable",
  "519": "Unavailable",
  "520": "Unavailable",
  "521": "Unavailable",
  "522": "Unavailable",
  "523": "Unavailable",
  "524": "Unavailable",
  "525": "Unavailable",
  "526": "Unavailable",
  "527": "Unavailable",
  "528": "Unavailable",
  "529": "Unavailable",
  "530": "Unavailable",
  "531": "Unavailable",
  "532": "Unavailable",
  "533": "Unavailable",
  "534": "Unavailable",
  "535": "Unavailable",
  "536": "Unavailable",
  "537": "Unavailable",
  "538": "Unavailable",
  "539": "Unavailable",
  "540": "Unavailable",
  "541": "Unavailable",
  "542": "Unavailable",
  "543": "Unavailable",
  "544": "Unavailable",
  "545": "Unavailable",
  "546": "Unavailable",
  "547": "Unavailable",
  "548": "Modificação de Grande Jagras",
  "549": "Aumenta um pouco o poder de ataque.\r\n<STYL MOJI_YELLOW_DEFAULT>(Melhoria nível 1)</STYL>",
  "550": "Modificação de Jyuratodus",
  "551": "Aumenta um pouco o dano elemental e\r\nde status anormal.\r\n<STYL MOJI_YELLOW_DEFAULT>(Melhoria nível 1)</STYL>",
  "552": "Modificação de Grande Girros",
  "553": "Aumenta um pouco a afinidade.\r\n<STYL MOJI_YELLOW_DEFAULT>(Melhoria nível 1)</STYL>",
  "554": "Modificação de Barroth",
  "555": "Acrescenta defesa ao seu equipamento.\r\n<STYL MOJI_YELLOW_DEFAULT>(Melhoria nível 1)</STYL>",
  "556": "Modificação de Tobi-Kadachi",
  "557": "Aumenta um pouco a afinidade.\r\n<STYL MOJI_YELLOW_DEFAULT>(Melhoria nível 2)</STYL>",
  "558": "Modificação de Banbaro",
  "559": "Aumenta um pouco o poder de ataque.\r\n<STYL MOJI_YELLOW_DEFAULT>(Melhoria nível 2)</STYL>",
  "560": "Modificação de Anjanath",
  "561": "Aumenta um pouco o dano elemental e\r\nde status anormal.\r\n<STYL MOJI_YELLOW_DEFAULT>(Melhoria nível 2)</STYL>",
  "562": "Modificação de Legiana",
  "563": "Aumenta um pouco o dano elemental e\r\nde status anormal.\r\n<STYL MOJI_YELLOW_DEFAULT>(Melhoria nível 3)</STYL>",
  "564": "Modificação de Rathalos",
  "565": "Aumenta um pouco o poder de ataque.\r\n<STYL MOJI_YELLOW_DEFAULT>(Melhoria nível 3)</STYL>",
  "566": "Modificação de Nargacuga",
  "567": "Aumenta um pouco a afinidade.\r\n<STYL MOJI_YELLOW_DEFAULT>(Melhoria nível 3)</STYL>",
  "568": "Modificação de Glavenus",
  "569": "Acrescenta defesa ao seu equipamento.\r\n<STYL MOJI_YELLOW_DEFAULT>(Melhoria nível 4)</STYL>",
  "570": "Mod. de Anjanath Fulgurante",
  "571": "Aumenta um pouco o dano elemental e\r\nde status anormal.\r\n<STYL MOJI_YELLOW_DEFAULT>(Melhoria nível 4)</STYL>",
  "572": "Modificação Glavenus Ácido",
  "573": "Aumenta um pouco o poder de ataque.\r\n<STYL MOJI_YELLOW_DEFAULT>(Melhoria nível 4)</STYL>",
  "574": "Modificação de Yian Garuga",
  "575": "Aumenta um pouco a afinidade.\r\n<STYL MOJI_YELLOW_DEFAULT>(Melhoria nível 4)</STYL>",
  "576": "Modificação de Bazelgeuse",
  "577": "Aumenta um pouco o dano elemental e\r\nde status anormal.\r\n<STYL MOJI_YELLOW_DEFAULT>(Melhoria nível 5)</STYL>",
  "578": "Modificação de Vaal Hazak",
  "579": "Aumenta um pouco a afinidade.\r\n<STYL MOJI_YELLOW_DEFAULT>(Melhoria nível 5)</STYL>",
  "580": "Modificação de Nergigante",
  "581": "Aumenta um pouco o poder de ataque.\r\n<STYL MOJI_YELLOW_DEFAULT>(Melhoria nível 5)</STYL>",
  "582": "Modificação de Brachydios",
  "583": "Aumenta um pouco o dano de ataque.\r\n<STYL MOJI_YELLOW_DEFAULT>(Melhoria nível 6)</STYL>",
  "584": "Modificação de Bazelgeuse+",
  "585": "Aumenta um pouco o dano elemental e\r\nde status anormal.\r\n<STYL MOJI_YELLOW_DEFAULT>(Melhoria nível 6)</STYL>",
  "586": "Modificação de Vaal Hazak+",
  "587": "Aumenta um pouco a afinidade.\r\n<STYL MOJI_YELLOW_DEFAULT>(Melhoria nível 6)</STYL>",
  "588": "Modificação de Nergigante+",
  "589": "Aumenta razoavelmente o poder de ataque.\r\n<STYL MOJI_YELLOW_DEFAULT>(Melhoria nível 7)</STYL>",
  "590": "Modificação de Legiana+",
  "591": "Aumenta razoavelmente a afinidade.\r\n<STYL MOJI_YELLOW_DEFAULT>(Melhoria nível 7)</STYL>",
  "592": "Modificação de Xeno'jiiva",
  "593": "Aumenta um pouco a afiação.\r\n<STYL MOJI_YELLOW_DEFAULT>(Melhoria nível 7)</STYL>",
  "594": "Unavailable",
  "595": "Unavailable",
  "596": "Unavailable",
  "597": "Unavailable",
  "598": "Unavailable",
  "599": "Unavailable",
  "600": "Unavailable",
  "601": "Unavailable",
  "602": "Unavailable",
  "603": "Unavailable",
  "604": "Unavailable",
  "605": "Unavailable",
  "606": "Unavailable",
  "607": "Unavailable",
  "608": "Unavailable",
  "609": "Unavailable",
  "610": "Unavailable",
  "611": "Unavailable",
  "612": "Unavailable",
  "613": "Unavailable",
  "614": "Unavailable",
  "615": "Unavailable",
  "616": "Unavailable",
  "617": "Unavailable",
  "618": "Unavailable",
  "619": "Unavailable",
  "620": "Unavailable",
  "621": "Unavailable",
  "622": "Unavailable",
  "623": "Unavailable",
  "624": "Unavailable",
  "625": "Unavailable",
  "626": "Modificação de Grande Jagras",
  "627": "Aumenta um pouco o poder de ataque.\r\n<STYL MOJI_YELLOW_DEFAULT>(Melhoria nível 1)</STYL>",
  "628": "Modificação de Pukei-Pukei",
  "629": "Aumenta um pouco o dano elemental e\r\nde status anormal.\r\n<STYL MOJI_YELLOW_DEFAULT>(Melhoria nível 1)</STYL>",
  "630": "Modificação de Barroth",
  "631": "Acrescenta defesa ao seu equipamento.\r\n<STYL MOJI_YELLOW_DEFAULT>(Melhoria nível 1)</STYL>",
  "632": "Modificação de Paolumu",
  "633": "Aumenta um pouco a afinidade.\r\n<STYL MOJI_YELLOW_DEFAULT>(Melhoria nível 1)</STYL>",
  "634": "Modificação de Banbaro",
  "635": "Acrescenta defesa ao seu equipamento.\r\n<STYL MOJI_YELLOW_DEFAULT>(Melhoria nível 2)</STYL>",
  "636": "Modificação Paolumu Beladona",
  "637": "Aumenta um pouco a afinidade.\r\n<STYL MOJI_YELLOW_DEFAULT>(Melhoria nível 2)</STYL>",
  "638": "Modificação Pukei Coralino",
  "639": "Aumenta um pouco o dano elemental e\r\nde status anormal.\r\n<STYL MOJI_YELLOW_DEFAULT>(Melhoria nível 2)</STYL>",
  "640": "Modificação de Diablos",
  "641": "Aumenta um pouco o poder de ataque.\r\n<STYL MOJI_YELLOW_DEFAULT>(Melhoria nível 2)</STYL>",
  "642": "Modificação de Legiana",
  "643": "Aumenta um pouco o dano elemental e\r\nde status anormal.\r\n<STYL MOJI_YELLOW_DEFAULT>(Melhoria nível 3)</STYL>",
  "644": "Modificação de Rathalos",
  "645": "Aumenta um pouco a afinidade.\r\n<STYL MOJI_YELLOW_DEFAULT>(Melhoria nível 3)</STYL>",
  "646": "Modificação de Glavenus",
  "647": "Acrescenta defesa ao seu equipamento.\r\n<STYL MOJI_YELLOW_DEFAULT>(Melhoria nível 3)</STYL>",
  "648": "Modificação de Tigrex",
  "649": "Aumenta um pouco o poder de ataque.\r\n<STYL MOJI_YELLOW_DEFAULT>(Melhoria nível 3)</STYL>",
  "650": "Modificação de Yian Garuga",
  "651": "Aumenta um pouco a afinidade.\r\n<STYL MOJI_YELLOW_DEFAULT>(Melhoria nível 4)</STYL>",
  "652": "Modificação Glavenus Ácido",
  "653": "Acrescenta defesa ao seu equipamento.\r\n<STYL MOJI_YELLOW_DEFAULT>(Melhoria nível 4)</STYL>",
  "654": "Modificação Rathalos Lazúli",
  "655": "Aumenta um pouco o poder de ataque.\r\n<STYL MOJI_YELLOW_DEFAULT>(Melhoria nível 4)</STYL>",
  "656": "Modificação de Zinogre",
  "657": "Aumenta um pouco o dano elemental e\r\nde status anormal.\r\n<STYL MOJI_YELLOW_DEFAULT>(Melhoria nível 4)</STYL>",
  "658": "Modificação de Tigrex Bruto",
  "659": "Acrescenta defesa ao seu equipamento.\r\n<STYL MOJI_YELLOW_DEFAULT>(Melhoria nível 5)</STYL>",
  "660": "Modificação de Bazelgeuse",
  "661": "Aumenta um pouco o dano elemental e\r\nde status anormal.\r\n<STYL MOJI_YELLOW_DEFAULT>(Melhoria nível 5)</STYL>",
  "662": "Modificação de Vaal Hazak",
  "663": "Aumenta um pouco a afinidade.\r\n<STYL MOJI_YELLOW_DEFAULT>(Melhoria nível 5)</STYL>",
  "664": "Modificação de Nergigante",
  "665": "Aumenta um pouco o poder de ataque.\r\n<STYL MOJI_YELLOW_DEFAULT>(Melhoria nível 5)</STYL>",
  "666": "Modificação de Uragaan",
  "667": "Acrescenta defesa ao seu equipamento.\r\n<STYL MOJI_YELLOW_DEFAULT>(Melhoria nível 6)</STYL>",
  "668": "Modificação de Brachydios",
  "669": "Aumenta um pouco o dano de ataque.\r\n<STYL MOJI_YELLOW_DEFAULT>(Melhoria nível 6)</STYL>",
  "670": "Modificação de Bazelgeuse+",
  "671": "Aumenta um pouco o dano elemental e\r\nde status anormal.\r\n<STYL MOJI_YELLOW_DEFAULT>(Melhoria nível 6)</STYL>",
  "672": "Modificação de Vaal Hazak+",
  "673": "Aumenta um pouco a afinidade.\r\n<STYL MOJI_YELLOW_DEFAULT>(Melhoria nível 6)</STYL>",
  "674": "Modificação de Nergigante+",
  "675": "Aumenta razoavelmente o poder de ataque.\r\n<STYL MOJI_YELLOW_DEFAULT>(Melhoria nível 7)</STYL>",
  "676": "Mod. de Zinogre Tenebroso",
  "677": "Aumenta razoavelmente a afinidade.\r\n<STYL MOJI_YELLOW_DEFAULT>(Melhoria nível 7)</STYL>",
  "678": "Modificação de Xeno'jiiva",
  "679": "Aumenta um pouco a afiação.\r\n<STYL MOJI_YELLOW_DEFAULT>(Melhoria nível 7)</STYL>",
  "680": "Unavailable",
  "681": "Unavailable",
  "682": "Unavailable",
  "683": "Unavailable",
  "684": "Unavailable",
  "685": "Unavailable",
  "686": "Unavailable",
  "687": "Unavailable",
  "688": "Unavailable",
  "689": "Unavailable",
  "690": "Unavailable",
  "691": "Unavailable",
  "692": "Unavailable",
  "693": "Unavailable",
  "694": "Unavailable",
  "695": "Unavailable",
  "696": "Unavailable",
  "697": "Unavailable",
  "698": "Unavailable",
  "699": "Unavailable",
  "700": "Unavailable",
  "701": "Unavailable",
  "702": "Unavailable",
  "703": "Unavailable",
  "704": "Modificação de Grande Jagras",
  "705": "Aumenta um pouco o poder de ataque.\r\n<STYL MOJI_YELLOW_DEFAULT>(Melhoria nível 1)</STYL>",
  "706": "Modificação de Jyuratodus",
  "707": "Aumenta um pouco o dano elemental e\r\nde status anormal.\r\n<STYL MOJI_YELLOW_DEFAULT>(Melhoria nível 1)</STYL>",
  "708": "Modificação de Grande Girros",
  "709": "Aumenta um pouco a afinidade.\r\n<STYL MOJI_YELLOW_DEFAULT>(Melhoria nível 1)</STYL>",
  "710": "Modificação de Dodogama",
  "711": "Acrescenta defesa ao seu equipamento.\r\n<STYL MOJI_YELLOW_DEFAULT>(Melhoria nível 1)</STYL>",
  "712": "Modificação de Tobi-Kadachi",
  "713": "Aumenta um pouco o dano elemental e\r\nde status anormal.\r\n<STYL MOJI_YELLOW_DEFAULT>(Melhoria nível 2)</STYL>",
  "714": "Modificação de Beotodus",
  "715": "Aumenta um pouco o poder de ataque.\r\n<STYL MOJI_YELLOW_DEFAULT>(Melhoria nível 2)</STYL>",
  "716": "Modificação Kadachi Vípero",
  "717": "Aumenta um pouco a afinidade.\r\n<STYL MOJI_YELLOW_DEFAULT>(Melhoria nível 2)</STYL>",
  "718": "Modificação de Odogaron",
  "719": "Aumenta um pouco a afinidade.\r\n<STYL MOJI_YELLOW_DEFAULT>(Melhoria nível 3)</STYL>",
  "720": "Modificação de Rathalos",
  "721": "Aumenta um pouco o dano elemental e\r\nde status anormal.\r\n<STYL MOJI_YELLOW_DEFAULT>(Melhoria nível 3)</STYL>",
  "722": "Modificação de Diablos",
  "723": "Aumenta um pouco o poder de ataque.\r\n<STYL MOJI_YELLOW_DEFAULT>(Melhoria nível 3)</STYL>",
  "724": "Modificação de Nargacuga",
  "725": "Aumenta um pouco a afinidade.\r\n<STYL MOJI_YELLOW_DEFAULT>(Melhoria nível 4)</STYL>",
  "726": "Modificação de Tigrex",
  "727": "Aumenta um pouco o poder de ataque.\r\n<STYL MOJI_YELLOW_DEFAULT>(Melhoria nível 4)</STYL>",
  "728": "Modificação de Diablos Negra",
  "729": "Aumenta um pouco o dano elemental e\r\nde status anormal.\r\n<STYL MOJI_YELLOW_DEFAULT>(Melhoria nível 4)</STYL>",
  "730": "Modificação de Tigrex Bruto",
  "731": "Acrescenta defesa ao seu equipamento.\r\n<STYL MOJI_YELLOW_DEFAULT>(Melhoria nível 5)</STYL>",
  "732": "Modificação de Namielle",
  "733": "Aumenta um pouco a afinidade.\r\n<STYL MOJI_YELLOW_DEFAULT>(Melhoria nível 5)</STYL>",
  "734": "Modificação de Vaal Hazak",
  "735": "Aumenta um pouco o dano elemental e\r\nde status anormal.\r\n<STYL MOJI_YELLOW_DEFAULT>(Melhoria nível 5)</STYL>",
  "736": "Modificação de Nergigante",
  "737": "Aumenta um pouco o poder de ataque.\r\n<STYL MOJI_YELLOW_DEFAULT>(Melhoria nível 5)</STYL>",
  "738": "Modificação de Vaal Hazak+",
  "739": "Aumenta um pouco o dano de ataque.\r\n<STYL MOJI_YELLOW_DEFAULT>(Melhoria nível 6)</STYL>",
  "740": "Modificação de Nergigante+",
  "741": "Aumenta razoavelmente o poder de ataque.\r\n<STYL MOJI_YELLOW_DEFAULT>(Melhoria nível 7)</STYL>",
  "742": "Mod. de Zinogre Tenebroso",
  "743": "Aumenta razoavelmente a afinidade.\r\n<STYL MOJI_YELLOW_DEFAULT>(Melhoria nível 7)</STYL>",
  "744": "Modificação de Xeno'jiiva",
  "745": "Aumenta um pouco a afiação.\r\n<STYL MOJI_YELLOW_DEFAULT>(Melhoria nível 7)</STYL>",
  "746": "Unavailable",
  "747": "Unavailable",
  "748": "Unavailable",
  "749": "Unavailable",
  "750": "Unavailable",
  "751": "Unavailable",
  "752": "Unavailable",
  "753": "Unavailable",
  "754": "Unavailable",
  "755": "Unavailable",
  "756": "Unavailable",
  "757": "Unavailable",
  "758": "Unavailable",
  "759": "Unavailable",
  "760": "Unavailable",
  "761": "Unavailable",
  "762": "Unavailable",
  "763": "Unavailable",
  "764": "Unavailable",
  "765": "Unavailable",
  "766": "Unavailable",
  "767": "Unavailable",
  "768": "Unavailable",
  "769": "Unavailable",
  "770": "Unavailable",
  "771": "Unavailable",
  "772": "Unavailable",
  "773": "Unavailable",
  "774": "Unavailable",
  "775": "Unavailable",
  "776": "Unavailable",
  "777": "Unavailable",
  "778": "Unavailable",
  "779": "Unavailable",
  "780": "Unavailable",
  "781": "Unavailable",
  "782": "Modificação de Kulu-Ya-Ku",
  "783": "Aumenta um pouco a afinidade.\r\n<STYL MOJI_YELLOW_DEFAULT>(Melhoria nível 1)</STYL>",
  "784": "Modificação de Pukei-Pukei",
  "785": "Aumenta um pouco o dano elemental e\r\nde status anormal.\r\n<STYL MOJI_YELLOW_DEFAULT>(Melhoria nível 1)</STYL>",
  "786": "Modificação de Tzitzi-Ya-Ku",
  "787": "Acrescenta defesa ao seu equipamento.\r\n<STYL MOJI_YELLOW_DEFAULT>(Melhoria nível 1)</STYL>",
  "788": "Modificação de Dodogama",
  "789": "Aumenta um pouco o poder de ataque.\r\n<STYL MOJI_YELLOW_DEFAULT>(Melhoria nível 1)</STYL>",
  "790": "Modificação de Tobi-Kadachi",
  "791": "Aumenta um pouco a afinidade.\r\n<STYL MOJI_YELLOW_DEFAULT>(Melhoria nível 2)</STYL>",
  "792": "Modificação de Beotodus",
  "793": "Acrescenta defesa ao seu equipamento.\r\n<STYL MOJI_YELLOW_DEFAULT>(Melhoria nível 2)</STYL>",
  "794": "Modificação Paolumu Beladona",
  "795": "Aumenta um pouco o poder de ataque.\r\n<STYL MOJI_YELLOW_DEFAULT>(Melhoria nível 2)</STYL>",
  "796": "Modificação Pukei Coralino",
  "797": "Aumenta um pouco o dano elemental e\r\nde status anormal.\r\n<STYL MOJI_YELLOW_DEFAULT>(Melhoria nível 2)</STYL>",
  "798": "Modificação Kadachi Vípero",
  "799": "Acrescenta defesa ao seu equipamento.\r\n<STYL MOJI_YELLOW_DEFAULT>(Melhoria nível 3)</STYL>",
  "800": "Modificação de Odogaron",
  "801": "Aumenta um pouco a afinidade.\r\n<STYL MOJI_YELLOW_DEFAULT>(Melhoria nível 3)</STYL>",
  "802": "Modificação de Rathalos",
  "803": "Aumenta um pouco o dano elemental e\r\nde status anormal.\r\n<STYL MOJI_YELLOW_DEFAULT>(Melhoria nível 3)</STYL>",
  "804": "Modificação de Diablos",
  "805": "Aumenta um pouco o poder de ataque.\r\n<STYL MOJI_YELLOW_DEFAULT>(Melhoria nível 3)</STYL>",
  "806": "Modificação de Nargacuga",
  "807": "Aumenta um pouco a afinidade.\r\n<STYL MOJI_YELLOW_DEFAULT>(Melhoria nível 4)</STYL>",
  "808": "Modificação de Tigrex",
  "809": "Aumenta um pouco o poder de ataque.\r\n<STYL MOJI_YELLOW_DEFAULT>(Melhoria nível 4)</STYL>",
  "810": "Modificação de Diablos Negra",
  "811": "Aumenta um pouco o dano elemental e\r\nde status anormal.\r\n<STYL MOJI_YELLOW_DEFAULT>(Melhoria nível 4)</STYL>",
  "812": "Modificação de Tigrex Bruto",
  "813": "Acrescenta defesa ao seu equipamento.\r\n<STYL MOJI_YELLOW_DEFAULT>(Melhoria nível 5)</STYL>",
  "814": "Modificação de Namielle",
  "815": "Aumenta um pouco a afinidade.\r\n<STYL MOJI_YELLOW_DEFAULT>(Melhoria nível 5)</STYL>",
  "816": "Modificação de Vaal Hazak",
  "817": "Aumenta um pouco o dano elemental e\r\nde status anormal.\r\n<STYL MOJI_YELLOW_DEFAULT>(Melhoria nível 5)</STYL>",
  "818": "Modificação de Nergigante",
  "819": "Aumenta um pouco o poder de ataque.\r\n<STYL MOJI_YELLOW_DEFAULT>(Melhoria nível 5)</STYL>",
  "820": "Modificação de Vaal Hazak+",
  "821": "Aumenta um pouco o dano de ataque.\r\n<STYL MOJI_YELLOW_DEFAULT>(Melhoria nível 6)</STYL>",
  "822": "Modificação de Nergigante+",
  "823": "Aumenta razoavelmente o poder de ataque.\r\n<STYL MOJI_YELLOW_DEFAULT>(Melhoria nível 7)</STYL>",
  "824": "Mod. de Zinogre Tenebroso",
  "825": "Aumenta razoavelmente a afinidade.\r\n<STYL MOJI_YELLOW_DEFAULT>(Melhoria nível 7)</STYL>",
  "826": "Modificação de Xeno'jiiva",
  "827": "Aumenta um pouco a afiação.\r\n<STYL MOJI_YELLOW_DEFAULT>(Melhoria nível 7)</STYL>",
  "828": "Unavailable",
  "829": "Unavailable",
  "830": "Unavailable",
  "831": "Unavailable",
  "832": "Unavailable",
  "833": "Unavailable",
  "834": "Unavailable",
  "835": "Unavailable",
  "836": "Unavailable",
  "837": "Unavailable",
  "838": "Unavailable",
  "839": "Unavailable",
  "840": "Unavailable",
  "841": "Unavailable",
  "842": "Unavailable",
  "843": "Unavailable",
  "844": "Unavailable",
  "845": "Unavailable",
  "846": "Unavailable",
  "847": "Unavailable",
  "848": "Unavailable",
  "849": "Unavailable",
  "850": "Unavailable",
  "851": "Unavailable",
  "852": "Unavailable",
  "853": "Unavailable",
  "854": "Unavailable",
  "855": "Unavailable",
  "856": "Unavailable",
  "857": "Unavailable",
  "858": "Unavailable",
  "859": "Unavailable",
  "860": "Modificação de Kulu-Ya-Ku",
  "861": "Aumenta um pouco a afinidade.\r\n<STYL MOJI_YELLOW_DEFAULT>(Melhoria nível 1)</STYL>",
  "862": "Modificação de Pukei-Pukei",
  "863": "Acrescenta defesa ao seu equipamento.\r\n<STYL MOJI_YELLOW_DEFAULT>(Melhoria nível 1)</STYL>",
  "864": "Modificação de Tobi-Kadachi",
  "865": "Aumenta um pouco o dano elemental e\r\nde status anormal.\r\n<STYL MOJI_YELLOW_DEFAULT>(Melhoria nível 1)</STYL>",
  "866": "Modificação de Banbaro",
  "867": "Aumenta um pouco o poder de ataque.\r\n<STYL MOJI_YELLOW_DEFAULT>(Melhoria nível 1)</STYL>",
  "868": "Modificação de Anjanath",
  "869": "Aumenta um pouco o poder de ataque.\r\n<STYL MOJI_YELLOW_DEFAULT>(Melhoria nível 2)</STYL>",
  "870": "Modificação de Rathian Rosa",
  "871": "Aumenta um pouco o dano elemental e\r\nde status anormal.\r\n<STYL MOJI_YELLOW_DEFAULT>(Melhoria nível 2)</STYL>",
  "872": "Modificação Paolumu Beladona",
  "873": "Aumenta um pouco a afinidade.\r\n<STYL MOJI_YELLOW_DEFAULT>(Melhoria nível 2)</STYL>",
  "874": "Modificação Pukei Coralino",
  "875": "Acrescenta defesa ao seu equipamento.\r\n<STYL MOJI_YELLOW_DEFAULT>(Melhoria nível 2)</STYL>",
  "876": "Modificação de Legiana",
  "877": "Aumenta um pouco o dano elemental e\r\nde status anormal.\r\n<STYL MOJI_YELLOW_DEFAULT>(Melhoria nível 3)</STYL>",
  "878": "Modificação de Rathalos",
  "879": "Aumenta um pouco a afinidade.\r\n<STYL MOJI_YELLOW_DEFAULT>(Melhoria nível 3)</STYL>",
  "880": "Modificação de Diablos",
  "881": "Acrescenta defesa ao seu equipamento.\r\n<STYL MOJI_YELLOW_DEFAULT>(Melhoria nível 3)</STYL>",
  "882": "Modificação de Glavenus",
  "883": "Aumenta um pouco o poder de ataque.\r\n<STYL MOJI_YELLOW_DEFAULT>(Melhoria nível 3)</STYL>",
  "884": "Modificação de Tigrex",
  "885": "Aumenta um pouco o poder de ataque.\r\n<STYL MOJI_YELLOW_DEFAULT>(Melhoria nível 4)</STYL>",
  "886": "Mod. de Anjanath Fulgurante",
  "887": "Aumenta um pouco o dano elemental e\r\nde status anormal.\r\n<STYL MOJI_YELLOW_DEFAULT>(Melhoria nível 4)</STYL>",
  "888": "Modificação Rathalos Lazúli",
  "889": "Aumenta um pouco a afinidade.\r\n<STYL MOJI_YELLOW_DEFAULT>(Melhoria nível 4)</STYL>",
  "890": "Modificação Glavenus Ácido",
  "891": "Acrescenta defesa ao seu equipamento.\r\n<STYL MOJI_YELLOW_DEFAULT>(Melhoria nível 4)</STYL>",
  "892": "Modificação de Tigrex Bruto",
  "893": "Aumenta um pouco a afinidade.\r\n<STYL MOJI_YELLOW_DEFAULT>(Melhoria nível 5)</STYL>",
  "894": "Modificação de Vaal Hazak",
  "895": "Aumenta um pouco o dano elemental e\r\nde status anormal.\r\n<STYL MOJI_YELLOW_DEFAULT>(Melhoria nível 5)</STYL>",
  "896": "Modificação de Nergigante",
  "897": "Aumenta um pouco o poder de ataque.\r\n<STYL MOJI_YELLOW_DEFAULT>(Melhoria nível 5)</STYL>",
  "898": "Modificação de Vaal Hazak+",
  "899": "Aumenta um pouco o dano de ataque.\r\n<STYL MOJI_YELLOW_DEFAULT>(Melhoria nível 6)</STYL>",
  "900": "Modificação de Nergigante+",
  "901": "Aumenta razoavelmente o poder de ataque.\r\n<STYL MOJI_YELLOW_DEFAULT>(Melhoria nível 7)</STYL>",
  "902": "Modificação de Barioth",
  "903": "Aumenta razoavelmente a afinidade.\r\n<STYL MOJI_YELLOW_DEFAULT>(Melhoria nível 7)</STYL>",
  "904": "Modificação de Xeno'jiiva",
  "905": "Aumenta um pouco o dano elemental e\r\nde status anormal.\r\n<STYL MOJI_YELLOW_DEFAULT>(Melhoria nível 7)</STYL>",
  "906": "Modificação Rathian Dourada",
  "907": "Aumenta um pouco o dano elemental e\r\nde status anormal.\r\n<STYL MOJI_YELLOW_DEFAULT>(Melhoria nível 6)</STYL>",
  "908": "Mod. de Rathalos Prateado",
  "909": "Aumenta um pouco a afinidade.\r\n<STYL MOJI_YELLOW_DEFAULT>(Melhoria nível 6)</STYL>",
  "910": "Unavailable",
  "911": "Unavailable",
  "912": "Unavailable",
  "913": "Unavailable",
  "914": "Unavailable",
  "915": "Unavailable",
  "916": "Unavailable",
  "917": "Unavailable",
  "918": "Unavailable",
  "919": "Unavailable",
  "920": "Unavailable",
  "921": "Unavailable",
  "922": "Unavailable",
  "923": "Unavailable",
  "924": "Unavailable",
  "925": "Unavailable",
  "926": "Unavailable",
  "927": "Unavailable",
  "928": "Unavailable",
  "929": "Unavailable",
  "930": "Unavailable",
  "931": "Unavailable",
  "932": "Unavailable",
  "933": "Unavailable",
  "934": "Unavailable",
  "935": "Unavailable",
  "936": "Unavailable",
  "937": "Unavailable",
  "938": "Modificação de Grande Jagras",
  "939": "Aumenta um pouco o poder de ataque.\r\n<STYL MOJI_YELLOW_DEFAULT>(Melhoria nível 1)</STYL>",
  "940": "Modificação de Pukei-Pukei",
  "941": "Acrescenta defesa ao seu equipamento.\r\n<STYL MOJI_YELLOW_DEFAULT>(Melhoria nível 1)</STYL>",
  "942": "Modificação de Tzitzi-Ya-Ku",
  "943": "Aumenta um pouco a afinidade.\r\n<STYL MOJI_YELLOW_DEFAULT>(Melhoria nível 1)</STYL>",
  "944": "Modificação de Tobi-Kadachi",
  "945": "Aumenta um pouco a afinidade.\r\n<STYL MOJI_YELLOW_DEFAULT>(Melhoria nível 2)</STYL>",
  "946": "Modificação de Dodogama",
  "947": "Acrescenta defesa ao seu equipamento.\r\n<STYL MOJI_YELLOW_DEFAULT>(Melhoria nível 2)</STYL>",
  "948": "Modificação de Radobaan",
  "949": "Aumenta um pouco o poder de ataque.\r\n<STYL MOJI_YELLOW_DEFAULT>(Melhoria nível 2)</STYL>",
  "950": "Modificação Paolumu Beladona",
  "951": "Aumenta um pouco o poder de ataque.\r\n<STYL MOJI_YELLOW_DEFAULT>(Melhoria nível 3)</STYL>",
  "952": "Modificação Pukei Coralino",
  "953": "Acrescenta defesa ao seu equipamento.\r\n<STYL MOJI_YELLOW_DEFAULT>(Melhoria nível 3)</STYL>",
  "954": "Modificação Kadachi Vípero",
  "955": "Aumenta um pouco a afinidade.\r\n<STYL MOJI_YELLOW_DEFAULT>(Melhoria nível 3)</STYL>",
  "956": "Modificação de Anjanath",
  "957": "Aumenta um pouco a afinidade.\r\n<STYL MOJI_YELLOW_DEFAULT>(Melhoria nível 4)</STYL>",
  "958": "Modificação de Diablos",
  "959": "Aumenta um pouco o poder de ataque.\r\n<STYL MOJI_YELLOW_DEFAULT>(Melhoria nível 4)</STYL>",
  "960": "Modificação de Namielle",
  "961": "Aumenta um pouco a afinidade.\r\n<STYL MOJI_YELLOW_DEFAULT>(Melhoria nível 5)</STYL>",
  "962": "Modificação de Nergigante",
  "963": "Aumenta um pouco o poder de ataque.\r\n<STYL MOJI_YELLOW_DEFAULT>(Melhoria nível 5)</STYL>",
  "964": "Modificação Zorah Magdaros",
  "965": "Aumenta um pouco o dano de ataque.\r\n<STYL MOJI_YELLOW_DEFAULT>(Melhoria nível 6)</STYL>",
  "966": "Modificação de Nergigante+",
  "967": "Aumenta razoavelmente o poder de ataque.\r\n<STYL MOJI_YELLOW_DEFAULT>(Melhoria nível 7)</STYL>",
  "968": "Modificação de Barioth",
  "969": "Aumenta razoavelmente a afinidade.\r\n<STYL MOJI_YELLOW_DEFAULT>(Melhoria nível 7)</STYL>",
  "970": "Modificação de Xeno'jiiva",
  "971": "Aumenta razoavelmente o dano elemental e\r\nde status anormal da sua munição.\r\n<STYL MOJI_YELLOW_DEFAULT>(Melhoria nível 7)</STYL>",
  "972": "Unavailable",
  "973": "Unavailable",
  "974": "Unavailable",
  "975": "Unavailable",
  "976": "Unavailable",
  "977": "Unavailable",
  "978": "Unavailable",
  "979": "Unavailable",
  "980": "Unavailable",
  "981": "Unavailable",
  "982": "Unavailable",
  "983": "Unavailable",
  "984": "Unavailable",
  "985": "Unavailable",
  "986": "Unavailable",
  "987": "Unavailable",
  "988": "Unavailable",
  "989": "Unavailable",
  "990": "Unavailable",
  "991": "Unavailable",
  "992": "Unavailable",
  "993": "Unavailable",
  "994": "Unavailable",
  "995": "Unavailable",
  "996": "Unavailable",
  "997": "Unavailable",
  "998": "Unavailable",
  "999": "Unavailable",
  "1000": "Unavailable",
  "1001": "Unavailable",
  "1002": "Unavailable",
  "1003": "Unavailable",
  "1004": "Unavailable",
  "1005": "Unavailable",
  "1006": "Unavailable",
  "1007": "Unavailable",
  "1008": "Unavailable",
  "1009": "Unavailable",
  "1010": "Unavailable",
  "1011": "Unavailable",
  "1012": "Unavailable",
  "1013": "Unavailable",
  "1014": "Unavailable",
  "1015": "Unavailable",
  "1016": "Modificação de Grande Jagras",
  "1017": "Aumenta um pouco o poder de ataque.\r\n<STYL MOJI_YELLOW_DEFAULT>(Melhoria nível 1)</STYL>",
  "1018": "Modificação de Barroth",
  "1019": "Acrescenta defesa ao seu equipamento.\r\n<STYL MOJI_YELLOW_DEFAULT>(Melhoria nível 1)</STYL>",
  "1020": "Modificação de Jyuratodus",
  "1021": "Aumenta um pouco o dano elemental e\r\nde status anormal da sua munição.\r\n<STYL MOJI_YELLOW_DEFAULT>(Melhoria nível 1)</STYL>",
  "1022": "Modificação de Paolumu",
  "1023": "Aumenta um pouco a afinidade.\r\n<STYL MOJI_YELLOW_DEFAULT>(Melhoria nível 1)</STYL>",
  "1024": "Modificação de Banbaro",
  "1025": "Aumenta um pouco o poder de ataque.\r\n<STYL MOJI_YELLOW_DEFAULT>(Melhoria nível 2)</STYL>",
  "1026": "Modificação de Anjanath",
  "1027": "Aumenta um pouco o dano elemental e\r\nde status anormal da sua munição.\r\n<STYL MOJI_YELLOW_DEFAULT>(Melhoria nível 2)</STYL>",
  "1028": "Modificação Paolumu Beladona",
  "1029": "Aumenta um pouco a afinidade.\r\n<STYL MOJI_YELLOW_DEFAULT>(Melhoria nível 2)</STYL>",
  "1030": "Modificação Pukei Coralino",
  "1031": "Acrescenta defesa ao seu equipamento.\r\n<STYL MOJI_YELLOW_DEFAULT>(Melhoria nível 2)</STYL>",
  "1032": "Modificação de Odogaron",
  "1033": "Aumenta um pouco a afinidade.\r\n<STYL MOJI_YELLOW_DEFAULT>(Melhoria nível 3)</STYL>",
  "1034": "Modificação de Rathalos",
  "1035": "Aumenta um pouco o dano elemental e\r\nde status anormal da sua munição.\r\n<STYL MOJI_YELLOW_DEFAULT>(Melhoria nível 3)</STYL>",
  "1036": "Modificação de Nargacuga",
  "1037": "Aumenta um pouco o poder de ataque.\r\n<STYL MOJI_YELLOW_DEFAULT>(Melhoria nível 3)</STYL>",
  "1038": "Modificação de Yian Garuga",
  "1039": "Acrescenta defesa ao seu equipamento.\r\n<STYL MOJI_YELLOW_DEFAULT>(Melhoria nível 3)</STYL>",
  "1040": "Modificação de Glavenus",
  "1041": "Aumenta um pouco o poder de ataque.\r\n<STYL MOJI_YELLOW_DEFAULT>(Melhoria nível 4)</STYL>",
  "1042": "Modificação de Tigrex",
  "1043": "Acrescenta defesa ao seu equipamento.\r\n<STYL MOJI_YELLOW_DEFAULT>(Melhoria nível 4)</STYL>",
  "1044": "Mod. de Anjanath Fulgurante",
  "1045": "Aumenta um pouco o dano elemental e\r\nde status anormal da sua munição.\r\n<STYL MOJI_YELLOW_DEFAULT>(Melhoria nível 4)</STYL>",
  "1046": "Modificação Rathalos Lazúli",
  "1047": "Aumenta um pouco a afinidade.\r\n<STYL MOJI_YELLOW_DEFAULT>(Melhoria nível 4)</STYL>",
  "1048": "Modificação de Tigrex Bruto",
  "1049": "Acrescenta defesa ao seu equipamento.\r\n<STYL MOJI_YELLOW_DEFAULT>(Melhoria nível 5)</STYL>",
  "1050": "Modificação de Bazelgeuse",
  "1051": "Aumenta um pouco o dano elemental e\r\nde status anormal da sua munição.\r\n<STYL MOJI_YELLOW_DEFAULT>(Melhoria nível 5)</STYL>",
  "1052": "Modificação de Vaal Hazak",
  "1053": "Aumenta um pouco a afinidade.\r\n<STYL MOJI_YELLOW_DEFAULT>(Melhoria nível 5)</STYL>",
  "1054": "Modificação de Nergigante",
  "1055": "Aumenta um pouco o poder de ataque.\r\n<STYL MOJI_YELLOW_DEFAULT>(Melhoria nível 5)</STYL>",
  "1056": "Modificação de Brachydios",
  "1057": "Aumenta um pouco o dano de ataque.\r\n<STYL MOJI_YELLOW_DEFAULT>(Melhoria nível 6)</STYL>",
  "1058": "Modificação de Bazelgeuse+",
  "1059": "Aumenta um pouco o dano elemental e\r\nde status anormal.\r\n<STYL MOJI_YELLOW_DEFAULT>(Melhoria nível 6)</STYL>",
  "1060": "Modificação de Nergigante+",
  "1061": "Aumenta razoavelmente o poder de ataque.\r\n<STYL MOJI_YELLOW_DEFAULT>(Melhoria nível 7)</STYL>",
  "1062": "Mod. de Zinogre Tenebroso",
  "1063": "Aumenta razoavelmente a afinidade.\r\n<STYL MOJI_YELLOW_DEFAULT>(Melhoria nível 7)</STYL>",
  "1064": "Modificação de Xeno'jiiva",
  "1065": "Aumenta razoavelmente o dano elemental e\r\nde status anormal.\r\n<STYL MOJI_YELLOW_DEFAULT>(Melhoria nível 7)</STYL>",
  "1066": "Mod. de Rathalos Prateado",
  "1067": "Aumenta um pouco a afinidade.\r\n<STYL MOJI_YELLOW_DEFAULT>(Melhoria nível 6)</STYL>",
  "1068": "Unavailable",
  "1069": "Unavailable",
  "1070": "Unavailable",
  "1071": "Unavailable",
  "1072": "Unavailable",
  "1073": "Unavailable",
  "1074": "Unavailable",
  "1075": "Unavailable",
  "1076": "Unavailable",
  "1077": "Unavailable",
  "1078": "Unavailable",
  "1079": "Unavailable",
  "1080": "Unavailable",
  "1081": "Unavailable",
  "1082": "Unavailable",
  "1083": "Unavailable",
  "1084": "Unavailable",
  "1085": "Unavailable",
  "1086": "Unavailable",
  "1087": "Unavailable",
  "1088": "Unavailable",
  "1089": "Unavailable",
  "1090": "Unavailable",
  "1091": "Unavailable",
  "1092": "Unavailable",
  "1093": "Unavailable"
}