{
  "0": "تعبير 1",
  "1": "متوفر منذ البداية",
  "2": "تعبير 2",
  "3": "متوفر منذ البداية",
  "4": "تعبير 3",
  "5": "متوفر منذ البداية",
  "6": "تعبير 4",
  "7": "متوفر منذ البداية",
  "8": "تعبير 5",
  "9": "متوفر منذ البداية",
  "10": "تعبير 6",
  "11": "متوفر منذ البداية",
  "12": "تعبير 7",
  "13": "متوفر منذ البداية",
  "14": "تعبير 8",
  "15": "متوفر منذ البداية",
  "16": "تعبير 9",
  "17": "متوفر منذ البداية",
  "18": "تعبير 10",
  "19": "متوفر منذ البداية",
  "20": "تعبير 11",
  "21": "متوفر منذ البداية",
  "22": "تعبير 12",
  "23": "متوفر منذ البداية",
  "24": "تعبير 13",
  "25": "متوفر منذ البداية",
  "26": "تعبير 14",
  "27": "متوفر منذ البداية",
  "28": "تعبير 15",
  "29": "متوفر منذ البداية",
  "30": "تعبير 16",
  "31": "متوفر منذ البداية",
  "32": "تعبير 17",
  "33": "متوفر منذ البداية",
  "34": "تعبير 18",
  "35": "متوفر منذ البداية",
  "36": "تعبير 19",
  "37": "متوفر منذ البداية",
  "38": "تعبير 20",
  "39": "متوفر منذ البداية",
  "40": "تعبير 21",
  "41": "متوفر منذ البداية",
  "42": "تعبير 22",
  "43": "متوفر منذ البداية",
  "44": "تعبير 23",
  "45": "متوفر منذ البداية",
  "46": "تعبير 24",
  "47": "متوفر منذ البداية",
  "48": "تعبير 25",
  "49": "متوفر منذ البداية",
  "50": "تعبير 26",
  "51": "متاح من خلال التنزيل",
  "52": "Unavailable",
  "53": "Unavailable",
  "54": "Unavailable",
  "55": "Unavailable",
  "56": "Unavailable",
  "57": "Unavailable",
  "58": "Unavailable",
  "59": "Unavailable",
  "60": "Unavailable",
  "61": "Unavailable",
  "62": "Unavailable",
  "63": "Unavailable",
  "64": "Unavailable",
  "65": "Unavailable",
  "66": "Unavailable",
  "67": "Unavailable",
  "68": "Unavailable",
  "69": "Unavailable",
  "70": "Unavailable",
  "71": "Unavailable",
  "72": "Unavailable",
  "73": "Unavailable"
}