{
  "0": "Mina 1",
  "1": "Dostępne od początku",
  "2": "Mina 2",
  "3": "Dostępne od początku",
  "4": "Mina 3",
  "5": "Dostępne od początku",
  "6": "Mina 4",
  "7": "Dostępne od początku",
  "8": "Mina 5",
  "9": "Dostępne od początku",
  "10": "Mina 6",
  "11": "Dostępne od początku",
  "12": "Mina 7",
  "13": "Dostępne od początku",
  "14": "Mina 8",
  "15": "Dostępne od początku",
  "16": "Mina 9",
  "17": "Dostępne od początku",
  "18": "Mina 10",
  "19": "Dostępne od początku",
  "20": "Mina 11",
  "21": "Dostępne od początku",
  "22": "Mina 12",
  "23": "Dostępne od początku",
  "24": "Mina 13",
  "25": "Dostępne od początku",
  "26": "Mina 14",
  "27": "Dostępne od początku",
  "28": "Mina 15",
  "29": "Dostępne od początku",
  "30": "Mina 16",
  "31": "Dostępne od początku",
  "32": "Mina 17",
  "33": "Dostępne od początku",
  "34": "Mina 18",
  "35": "Dostępne od początku",
  "36": "Mina 19",
  "37": "Dostępne od początku",
  "38": "Mina 20",
  "39": "Dostępne od początku",
  "40": "Mina 21",
  "41": "Dostępne od początku",
  "42": "Mina 22",
  "43": "Dostępne od początku",
  "44": "Mina 23",
  "45": "Dostępne od początku",
  "46": "Mina 24",
  "47": "Dostępne od początku",
  "48": "Mina 25",
  "49": "Dostępne od początku",
  "50": "Mina 26",
  "51": "Dostępne po pobraniu",
  "52": "Unavailable",
  "53": "Unavailable",
  "54": "Unavailable",
  "55": "Unavailable",
  "56": "Unavailable",
  "57": "Unavailable",
  "58": "Unavailable",
  "59": "Unavailable",
  "60": "Unavailable",
  "61": "Unavailable",
  "62": "Unavailable",
  "63": "Unavailable",
  "64": "Unavailable",
  "65": "Unavailable",
  "66": "Unavailable",
  "67": "Unavailable",
  "68": "Unavailable",
  "69": "Unavailable",
  "70": "Unavailable",
  "71": "Unavailable",
  "72": "Unavailable",
  "73": "Unavailable"
}