{
  "0": "Unavailable",
  "1": "Unavailable",
  "2": "Unavailable",
  "3": "독 내성",
  "4": "독 내성",
  "5": "독 상태에서 받는 데미지가 줄어든다.",
  "6": "마비 내성",
  "7": "Invalid Message",
  "8": "마비 상태의 시간을 단축한다.",
  "9": "수면 내성",
  "10": "Invalid Message",
  "11": "수면 상태의 시간을 단축한다.",
  "12": "기절 내성",
  "13": "Invalid Message",
  "14": "기절 상태의 시간을 단축한다.",
  "15": "진흙 내성",
  "16": "Invalid Message",
  "17": "몬스터가 발생시킨 진창에서의 \r\n행동 제한을 감소한다.",
  "18": "폭파 피해 내성",
  "19": "Invalid Message",
  "20": "폭파 피해에 대한 내성을 얻는다.",
  "21": "열상 내성",
  "22": "Invalid Message",
  "23": "열상 상태에 대한 내성을 얻는다.",
  "24": "방어력 DOWN 내성",
  "25": "Invalid Message",
  "26": "방어력 DOWN에 대한 내성을 얻는다.",
  "27": "Unavailable",
  "28": "Unavailable",
  "29": "Unavailable",
  "30": "Unavailable",
  "31": "Unavailable",
  "32": "Unavailable",
  "33": "귀마개",
  "34": "Invalid Message",
  "35": "대형 몬스터의 포효에 대한 내성을 지닌다.",
  "36": "풍압 내성",
  "37": "Invalid Message",
  "38": "풍압에 대한 내성을 얻는다.",
  "39": "내진",
  "40": "Invalid Message",
  "41": "지면 진동에 대한 내성을 얻는다.",
  "42": "거름 명인",
  "43": "Invalid Message",
  "44": "슬링어 거름탄을 맞힌 몬스터는\r\n도망칠 확률이 높아진다.",
  "45": "Unavailable",
  "46": "Unavailable",
  "47": "Unavailable",
  "48": "독기 환경 적응",
  "49": "Invalid Message",
  "50": "독기의 골짜기의 환경 데미지를 감소하고\r\n무효화한다.",
  "51": "열 데미지 무효",
  "52": "Invalid Message",
  "53": "더위나 열에 의한 데미지를\r\n무효화한다.",
  "54": "Unavailable",
  "55": "Unavailable",
  "56": "Unavailable",
  "57": "공격",
  "58": "Invalid Message",
  "59": "플레이어의 공격력을 올린다.\r\n레벨이 오르면 회심률에도 영향을 준다.",
  "60": "방어",
  "61": "Invalid Message",
  "62": "플레이어의 방어력을 올린다.\r\n레벨이 오르면 내성치에도 영향을 준다.",
  "63": "체력 증강",
  "64": "Invalid Message",
  "65": "플레이어의 체력을 올린다.",
  "66": "체력 회복량 UP",
  "67": "Invalid Message",
  "68": "체력 회복이 발생했을 때\r\n회복량이 오른다.",
  "69": "회복 속도",
  "70": "Invalid Message",
  "71": "데미지를 받았을 때\r\n붉은 게이지 부분의\r\n회복 속도가 상승한다.",
  "72": "불 내성",
  "73": "Invalid Message",
  "74": "플레이어의 불 내성을 올린다.\r\n레벨이 오르면 방어력에도\r\n영향을 준다.",
  "75": "물 내성",
  "76": "Invalid Message",
  "77": "플레이어의 물 내성을 올린다.\r\n레벨이 오르면 방어력에도\r\n영향을 준다.",
  "78": "얼음 내성",
  "79": "Invalid Message",
  "80": "플레이어의 얼음 내성을 올린다.\r\n레벨이 오르면 방어력에도\r\n영향을 준다.",
  "81": "번개 내성",
  "82": "Invalid Message",
  "83": "플레이어의 번개 내성을 올린다.\r\n레벨이 오르면 방어력에도\r\n영향을 준다.",
  "84": "용 내성",
  "85": "Invalid Message",
  "86": "플레이어의 용 내성을 올린다.\r\n레벨이 오르면 방어력에도\r\n영향을 준다.",
  "87": "속성 피해 내성",
  "88": "Invalid Message",
  "89": "모든 속성 피해 상태에 대한\r\n내성을 얻는다.",
  "90": "불속성 공격 강화",
  "91": "Invalid Message",
  "92": "불속성의 힘을 강화한다.\r\n<STYL MOJI_YELLOW_DEFAULT>(무기의 속성치 강화에는\r\n한계가 있습니다)</STYL>",
  "93": "물속성 공격 강화",
  "94": "Invalid Message",
  "95": "물속성의 힘을 강화한다.\r\n<STYL MOJI_YELLOW_DEFAULT>(무기의 속성치 강화에는\r\n한계가 있습니다)</STYL>",
  "96": "얼음속성 공격 강화",
  "97": "Invalid Message",
  "98": "얼음속성의 힘을 강화한다.\r\n<STYL MOJI_YELLOW_DEFAULT>(무기의 속성치 강화에는\r\n한계가 있습니다)</STYL>",
  "99": "번개속성 공격 강화",
  "100": "Invalid Message",
  "101": "번개속성의 힘을 강화한다.\r\n<STYL MOJI_YELLOW_DEFAULT>(무기의 속성치 강화에는\r\n한계가 있습니다)</STYL>",
  "102": "용속성 공격 강화",
  "103": "Invalid Message",
  "104": "용속성의 힘을 강화한다.\r\n<STYL MOJI_YELLOW_DEFAULT>(무기의 속성치 강화에는\r\n한계가 있습니다)</STYL>",
  "105": "독속성 강화",
  "106": "Invalid Message",
  "107": "독의 축적치를 강화한다.\r\n<STYL MOJI_YELLOW_DEFAULT>(무기의 속성치 강화에는\r\n한계가 있습니다)</STYL>",
  "108": "마비속성 강화",
  "109": "Invalid Message",
  "110": "마비의 축적치가 강화한다.\r\n<STYL MOJI_YELLOW_DEFAULT>(무기의 속성치 강화에는\r\n한계가 있습니다)</STYL>",
  "111": "수면속성 강화",
  "112": "Invalid Message",
  "113": "수면의 축적치를 강화한다.\r\n<STYL MOJI_YELLOW_DEFAULT>(무기의 속성치 강화에는\r\n한계가 있습니다)</STYL>",
  "114": "폭파속성 강화",
  "115": "Invalid Message",
  "116": "폭파의 축적치가 강화한다.\r\n<STYL MOJI_YELLOW_DEFAULT>(무기의 속성치 강화에는\r\n한계가 있습니다)</STYL>",
  "117": "통상탄/통상화살 강화",
  "118": "Invalid Message",
  "119": "보우건의 통상탄 또는\r\n활의 통상화살 공격력이 오른다.",
  "120": "관통탄/용화살 강화",
  "121": "Invalid Message",
  "122": "보우건의 관통탄 또는\r\n활의 용화살 공격력이 오른다.",
  "123": "산탄/강사 강화",
  "124": "산탄/강사 강화",
  "125": "보우건의 산탄 또는 활의 강사,\r\n용의 천천시의 공격력이 오른다.",
  "126": "독병 추가",
  "127": "Invalid Message",
  "128": "활 장비 중, 독병을 장착할 수 있게 한다.",
  "129": "마비병 추가",
  "130": "Invalid Message",
  "131": "활 장비 중, 마비병을\r\n장착할 수 있게 한다.",
  "132": "수면병 추가",
  "133": "Invalid Message",
  "134": "활 장비 중, 수면병을\r\n장착할 수 있게 한다.",
  "135": "Unavailable",
  "136": "Unavailable",
  "137": "Unavailable",
  "138": "폭파병 추가",
  "139": "Invalid Message",
  "140": "활 장비 중, 폭파병을\r\n장착할 수 있게 한다.",
  "141": "속성해방/장전 확장",
  "142": "Invalid Message",
  "143": "무기의 숨은 속성을 해제한다.\r\n보우건의 장전 수가 늘어난다.\r\n<STYL MOJI_YELLOW_DEFAULT>(장전 수에는 한계가 있습니다)</STYL>",
  "144": "간파",
  "145": "Invalid Message",
  "146": "회심률이 상승한다.",
  "147": "슈퍼회심",
  "148": "Invalid Message",
  "149": "회심 공격 시, 데미지가 증가한다.",
  "150": "약점 특효",
  "151": "Invalid Message",
  "152": "몬스터를 공격할 때 명중한 부위가\r\n꽤 효과적이면 회심률이 오른다.",
  "153": "Unavailable",
  "154": "Unavailable",
  "155": "Unavailable",
  "156": "집중",
  "157": "Invalid Message",
  "158": "태도, 쌍검, 슬래시액스, 차지액스의\r\n게이지와 대검, 해머, 활의 모으기\r\n속도가 빨라진다.",
  "159": "강화 지속",
  "160": "Invalid Message",
  "161": "태도, 쌍검, 조충곤, 슬래시액스,\r\n차지액스로 발생한 강화 상태의\r\n지속 시간을 길게 한다.",
  "162": "장인",
  "163": "Invalid Message",
  "164": "무기의 예리도 게이지가 늘어난다.\r\n단, 예리도 게이지의 한계 이상으로\r\n늘어나지는 않는다.",
  "165": "발도술【기】",
  "166": "Invalid Message",
  "167": "무기 발도 공격의 회심률이 오른다.",
  "168": "파괴왕",
  "169": "Invalid Message",
  "170": "대형 몬스터의 부위를\r\n파괴하기가 쉬워진다.",
  "171": "KO술",
  "172": "Invalid Message",
  "173": "몬스터를 기절 상태로 만들\r\n확률이 높아진다.",
  "174": "스태미나 탈취",
  "175": "Invalid Message",
  "176": "특정 공격을 통해 몬스터를\r\n피로하게 하는 효과가 상승한다.",
  "177": "탑승 명인",
  "178": "Invalid Message",
  "179": "몬스터에게 탑승하기가 쉬워진다.",
  "180": "비연",
  "181": "Invalid Message",
  "182": "점프 공격이 강화된다.",
  "183": "힘의 해방",
  "184": "Invalid Message",
  "185": "특정 조건을 만족시키면 일정 시간\r\n회심률이 상승하고, 스태미나를 고정적\r\n으로 소비하는 행동의 소비량이 감소한다.",
  "186": "도전자",
  "187": "Invalid Message",
  "188": "전투 중에 대형 몬스터가\r\n분노하면 공격력과 회심률이\r\n상승한다.",
  "189": "완전 충전",
  "190": "Invalid Message",
  "191": "체력이 최대일 때 공격력이 오른다.",
  "192": "재난대처능력",
  "193": "Invalid Message",
  "194": "체력이 최대치의 35％ 이하이면\r\n방어력과 공격력이 오른다.",
  "195": "불굴",
  "196": "불굴",
  "197": "일정 시간 동안, 힘이 다할 때마다 공격력과\r\n방어력이 오른다.<STYL MOJI_YELLOW_DEFAULT>(최대 2번까지)</STYL>",
  "198": "앙심",
  "199": "Invalid Message",
  "200": "체력 게이지에 빨간 부분이\r\n있는 동안 공격력이 오른다.",
  "201": "돌파구",
  "202": "Invalid Message",
  "203": "상태 이상 중에 회피 성능이 상승하고\r\n스태미나의 소비량도 줄어든다.",
  "204": "피리 명인",
  "205": "Invalid Message",
  "206": "수렵피리의 선율 효과\r\n지속 시간이 늘어난다.",
  "207": "포탄 장전 수 UP",
  "208": "Invalid Message",
  "209": "건랜스의 포격 장전 수,\r\n차지액스의 병 장전 수가 늘어난다.",
  "210": "특수 사격 강화",
  "211": "특수 사격 강화",
  "212": "보우건의 특수탄과\r\n활의 용화살, 용의 천천시\r\n위력이 상승한다.",
  "213": "포술",
  "214": "Invalid Message",
  "215": "건랜스의 포격, 용격포와 차지액스의\r\n병공격, 철갑유탄 등 폭발을 일으키는\r\n공격의 위력이 상승.",
  "216": "포격수",
  "217": "Invalid Message",
  "218": "발리스타, 대포의 위력이 오른다.",
  "219": "런너",
  "220": "Invalid Message",
  "221": "대시 등 서서히 스태미나를 소비하는\r\n행동의 스태미나 소비량이 감소한다.",
  "222": "체술",
  "223": "Invalid Message",
  "224": "회피 등 고정적으로 스태미나를\r\n소비하는 행동의 스태미나\r\n소비량이 감소한다.",
  "225": "뛰어들기",
  "226": "Invalid Message",
  "227": "대형 몬스터를 향해 점프\r\n회피가 가능해진다. 또한\r\n비거리도 늘어난다.",
  "228": "스태미나 급속 회복",
  "229": "Invalid Message",
  "230": "스태미나의 회복 속도가 빨라진다.",
  "231": "배고픔 내성",
  "232": "배고픔 내성",
  "233": "시간 경과에 따른 스태미나 게이지의\r\n최대치 감소를 억제한다.\r\n하지만 추위에 의한 감소는 억제할 수 없다.",
  "234": "회피 성능",
  "235": "Invalid Message",
  "236": "회피 시 무적 시간이 늘어난다.",
  "237": "회피 거리 UP",
  "238": "Invalid Message",
  "239": "회피 시의 이동 거리가 길어진다.",
  "240": "가드 성능",
  "241": "Invalid Message",
  "242": "가드 시에는 좀처럼 움츠리지 않게 되고,\r\n소비 스태미나도 줄어든다.",
  "243": "납도술",
  "244": "Invalid Message",
  "245": "무기를 집어넣는 속도가 빨라진다.",
  "246": "광역화",
  "247": "Invalid Message",
  "248": "일부 아이템을 사용했을 때의\r\n효과가 일정 범위 안에 있는\r\n동료에게도 작용한다.",
  "249": "아이템 사용 강화",
  "250": "Invalid Message",
  "251": "일부 아이템의 효과 시간이 늘어난다.",
  "252": "만족감",
  "253": "Invalid Message",
  "254": "먹거나 마시는 아이템을 일정 확률로\r\n한 번 더 사용할 수 있게 된다.",
  "255": "빨리 먹기",
  "256": "Invalid Message",
  "257": "고기나 아이템을 먹는 속도가 빨라진다.",
  "258": "숫돌 사용 고속화",
  "259": "Invalid Message",
  "260": "숫돌의 사용 시간이 짧아진다.",
  "261": "Unavailable",
  "262": "Unavailable",
  "263": "Unavailable",
  "264": "보머",
  "265": "Invalid Message",
  "266": "폭탄 계열 아이템의 데미지가 상승한다.",
  "267": "Unavailable",
  "268": "Unavailable",
  "269": "Unavailable",
  "270": "버섯 애호가",
  "271": "Invalid Message",
  "272": "평소에는 먹을 수 없는 버섯을\r\n먹을 수 있게 되어\r\n좋은 효과를 얻을 수 있다.",
  "273": "낚시 명인",
  "274": "Invalid Message",
  "275": "낚시를 잘하게 되는 스킬.",
  "276": "고기굽기 명인",
  "277": "Invalid Message",
  "278": "고기를 잘 굽게 되는 스킬.",
  "279": "운반의 달인",
  "280": "Invalid Message",
  "281": "운반 시 이동 속도가 증가하고,\r\n어느 정도 높은 곳에서 뛰어내려도\r\n운반 중인 물건을 떨어뜨리지 않는다.",
  "282": "채집의 달인",
  "283": "Invalid Message",
  "284": "채집 행동의 속도가 빨라지고,\r\n행동 중에 공격을 받아도\r\n움츠리지 않게 된다.",
  "285": "허니 헌터",
  "286": "Invalid Message",
  "287": "필드에서 벌꿀을 채취했을 때의\r\n취득 수가 증가한다.",
  "288": "갈무리 철인",
  "289": "Invalid Message",
  "290": "갈무리 도중에 공격을 받아도\r\n움츠리지 않는다.",
  "291": "정령의 가호",
  "292": "Invalid Message",
  "293": "플레이어가 받는 데미지를\r\n일정 확률로 감소시킨다.",
  "294": "동반자 지휘",
  "295": "Invalid Message",
  "296": "동반자의 공격력과 방어력이 강화된다.",
  "297": "식생학",
  "298": "Invalid Message",
  "299": "약초 등, 소비 아이템의\r\n취득 수가 증가한다.",
  "300": "지질학",
  "301": "Invalid Message",
  "302": "채취 포인트의 채취 횟수가 증가한다.",
  "303": "혼신",
  "304": "혼신",
  "305": "스태미나 게이지가 가득 찬 상태를\r\n잠시 유지하고 있으면\r\n회심률이 오른다.",
  "306": "슬링어 장전 수 UP",
  "307": "슬링어 장전 수 업",
  "308": "필드에서 취득하는 슬링어 탄의\r\n장전 수가 증가한다. 슬링어 \r\n전탄 발사 시 소모하는 탄 수를 억제한다.",
  "309": "잠복",
  "310": "Invalid Message",
  "311": "몬스터가 플레이어를 못 보고\r\n지나칠 확률이 증가한다.",
  "312": "움찔 감소",
  "313": "Invalid Message",
  "314": "적은 데미지를 받을 때 리액션을 줄인다.",
  "315": "안내벌레의 반응 거리 UP",
  "316": "Invalid Message",
  "317": "안내벌레의 반응 범위가 넓어진다.",
  "318": "앉아 이동 속도 UP",
  "319": "Invalid Message",
  "320": "앉아서 이동 속도가 빨라진다.",
  "321": "점프 철인",
  "322": "Invalid Message",
  "323": "점프 중에 공격을 받아도\r\n움츠리지 않게 된다.",
  "324": "환경 이용 지식",
  "325": "환경 이용 지식",
  "326": "면 포자풀이나, 얼음 내성 풀 등\r\n임의로 발동할 수 있는 환경 이용 시\r\n체력이 추가로 회복된다.",
  "327": "물가/쌓인 눈 적응",
  "328": "물가/쌓인 눈 적응",
  "329": "물가에 적응해서 행동할 수 있게 된다.\r\n눈이 쌓여 있는 장소 등 지형 효과로\r\n이동 속도가 느려지는 장소에도 적응한다.",
  "330": "Unavailable",
  "331": "Unavailable",
  "332": "Unavailable",
  "333": "클라이머",
  "334": "클라이머",
  "335": "벽이나 넝쿨에 매달린 상태의\r\n회피 이동이나 클러치 중 이동으로\r\n소비되는 스태미나양이 감소한다.",
  "336": "섬광 강화",
  "337": "Invalid Message",
  "338": "발생시킨 섬광이 효과를\r\n발휘할 확률이 높아진다.",
  "339": "Unavailable",
  "340": "Unavailable",
  "341": "Unavailable",
  "342": "연구자",
  "343": "Invalid Message",
  "344": "대형 몬스터의 조사 및 연구가\r\n진행하기 쉬워진다.\r\n<STYL MOJI_YELLOW_DEFAULT>(결과 화면에서 효과를 얻을 수 있음)</STYL>",
  "345": "곤충 표본의 달인",
  "346": "Invalid Message",
  "347": "곤충형의 소형 몬스터를 공격해서\r\n토벌해도 갈무리할 수 있는 상태로\r\n남을 확률이 높아진다.",
  "348": "독기 내성",
  "349": "Invalid Message",
  "350": "독기 침식 상태에 대한 내성을 얻는다.",
  "351": "추적의 달인",
  "352": "Invalid Message",
  "353": "안내벌레가 대형 몬스터에게 유도를\r\n시작하기까지 필요한 흔적의 수가\r\n줄어든다.",
  "354": "탐색자의 행운",
  "355": "Invalid Message",
  "356": "활성화되어 있는 채취 포인트의\r\n발생 확률이 오른다.",
  "357": "감지",
  "358": "Invalid Message",
  "359": "활성화되어 있는 채취 포인트를\r\n생태 MAP에서 알 수 있게 된다.",
  "360": "정비",
  "361": "Invalid Message",
  "362": "특수 장비를 다시 사용할 수 있게\r\n되기까지의 시간이 단축된다.",
  "363": "Unavailable",
  "364": "Unavailable",
  "365": "Unavailable",
  "366": "활주 강화",
  "367": "Invalid Message",
  "368": "슬라이딩을 실시하면 일정 시간\r\n회심률이 오른다.",
  "369": "용봉력 강화",
  "370": "Invalid Message",
  "371": "무기와 멸룡탄이 지닌 용봉력을\r\n강화한다.",
  "372": "위협",
  "373": "Invalid Message",
  "374": "소형 몬스터에게 들켜도\r\n전투 상태가 될 확률이 낮아진다.<STYL MOJI_YELLOW_DEFAULT>(갑충종\r\n등 일부 몬스터에는 효과가 없음)</STYL>",
  "375": "만악룡의 힘",
  "376": "Invalid Message",
  "377": "Unavailable",
  "378": "멸진룡의 굶주림",
  "379": "Invalid Message",
  "380": "Unavailable",
  "381": "시투룡의 명맥",
  "382": "Invalid Message",
  "383": "Unavailable",
  "384": "화룡의 힘",
  "385": "Invalid Message",
  "386": "Unavailable",
  "387": "각룡의 힘",
  "388": "Invalid Message",
  "389": "Unavailable",
  "390": "환수의 은혜",
  "391": "Invalid Message",
  "392": "Unavailable",
  "393": "앵화룡의 비기",
  "394": "Invalid Message",
  "395": "Unavailable",
  "396": "만악룡의 투지",
  "397": "Invalid Message",
  "398": "Unavailable",
  "399": "Unavailable",
  "400": "Unavailable",
  "401": "Unavailable",
  "402": "Unavailable",
  "403": "Unavailable",
  "404": "Unavailable",
  "405": "화룡의 비기",
  "406": "Invalid Message",
  "407": "Unavailable",
  "408": "각룡의 비기",
  "409": "Invalid Message",
  "410": "Unavailable",
  "411": "환수의 은총",
  "412": "Invalid Message",
  "413": "Unavailable",
  "414": "폭추룡의 수호",
  "415": "Invalid Message",
  "416": "Unavailable",
  "417": "Unavailable",
  "418": "Unavailable",
  "419": "Unavailable",
  "420": "Unavailable",
  "421": "Unavailable",
  "422": "Unavailable",
  "423": "Unavailable",
  "424": "Unavailable",
  "425": "Unavailable",
  "426": "폭린룡의 수호",
  "427": "Invalid Message",
  "428": "Unavailable",
  "429": "염왕룡의 무예",
  "430": "Invalid Message",
  "431": "Unavailable",
  "432": "강룡의 비상",
  "433": "Invalid Message",
  "434": "Unavailable",
  "435": "명등룡의 신비",
  "436": "Invalid Message",
  "437": "Unavailable",
  "438": "Unavailable",
  "439": "Unavailable",
  "440": "Unavailable",
  "441": "용산룡의 비기",
  "442": "Invalid Message",
  "443": "Unavailable",
  "444": "Unavailable",
  "445": "Unavailable",
  "446": "Unavailable",
  "447": "길드의 안내",
  "448": "Invalid Message",
  "449": "Unavailable",
  "450": "조사단의 안내",
  "451": "Invalid Message",
  "452": "Unavailable",
  "453": "풍표룡의 은혜",
  "454": "Invalid Message",
  "455": "Unavailable",
  "456": "풍표룡의 은총",
  "457": "Invalid Message",
  "458": "Unavailable",
  "459": "참조룡의 힘",
  "460": "Invalid Message",
  "461": "Unavailable",
  "462": "참조룡의 비기",
  "463": "Invalid Message",
  "464": "Unavailable",
  "465": "활 모으기 단계 해제",
  "466": "활 모으기 단계 해제",
  "467": "활의 모으기 단계가 1단계 증가.",
  "468": "심안/탄도 강화",
  "469": "심안/탄도 강화",
  "470": "공격이 튕겨 나가지 않는다.\r\n/탄과 화살이 최대 위력이\r\n되기까지의 거리가 짧아진다.",
  "471": "가드 강화",
  "472": "가드 강화",
  "473": "평소에는 가드할 수 없는 공격도\r\n가드할 수 있게 된다.",
  "474": "칼날 연마",
  "475": "강인연마",
  "476": "무기를 연마하면, 일정 시간\r\n동안 예리도가 떨어지지 않는다.",
  "477": "무속성 강화",
  "478": "무속성 강화",
  "479": "장비 중인 무속성 무기를\r\n강화한다.",
  "480": "근성",
  "481": "Invalid Message",
  "482": "체력이 일정량 이상 남아 있을 때\r\n체력을 초과하는 데미지를 받아도\r\n한 번만 힘이 다하지 않고 버틴다.",
  "483": "가속 재생",
  "484": "Invalid Message",
  "485": "지속적으로 몬스터에게 공격을\r\n성공시키면 체력이 회복된다. 무기\r\n종류에 따라 회복량이 달라진다.",
  "486": "명검/탄환 절약",
  "487": "Invalid Message",
  "488": "예리도 소모를 절반으로 억제한다.\r\n/가끔 보우건의 탄과 활의 병을\r\n소모하지 않고 발사할 수 있다.",
  "489": "염비룡의 은총",
  "490": "Invalid Message",
  "491": "Unavailable",
  "492": "용기사의 증표",
  "493": "Invalid Message",
  "494": "Unavailable",
  "495": "회심격【속성】",
  "496": "Invalid Message",
  "497": "공격으로 회심이 발생했을 때\r\n주는 속성 데미지(불, 물,\r\n번개, 얼음, 용)가 높아진다.",
  "498": "회심격【특수】",
  "499": "Invalid Message",
  "500": "공격으로 회심이 발생했을 때\r\n주는 상태 이상치(마비, 독,\r\n수면, 폭파)가 높아진다.",
  "501": "위쳐의 마음가짐",
  "502": "Invalid Message",
  "503": "Unavailable",
  "504": "아스테라의 축복",
  "505": "Invalid Message",
  "506": "Unavailable",
  "507": "뇌랑룡의 진수",
  "508": "뇌랑룡의 진수",
  "509": "Unavailable",
  "510": "굉룡의 진수",
  "511": "굉룡의 진수",
  "512": "Unavailable",
  "513": "신룡의 진수",
  "514": "신룡의 진수",
  "515": "Unavailable",
  "516": "쇄룡의 진수",
  "517": "쇄룡의 진수",
  "518": "Unavailable",
  "519": "참룡의 진수",
  "520": "참룡의 진수",
  "521": "Unavailable",
  "522": "은화룡의 진수",
  "523": "은화룡의 진수",
  "524": "Unavailable",
  "525": "금화룡의 진수",
  "526": "금화룡의 진수",
  "527": "Unavailable",
  "528": "지제룡의 신비",
  "529": "지제룡의 신비",
  "530": "Unavailable",
  "531": "명룡의 신비",
  "532": "명룡의 신비",
  "533": "Unavailable",
  "534": "빙룡의 신비",
  "535": "빙룡의 신비",
  "536": "Unavailable",
  "537": "태고의 신비",
  "538": "태고의 신비",
  "539": "Unavailable",
  "540": "조사단의 연금술",
  "541": "조사단의 연금술",
  "542": "Unavailable",
  "543": "교관의 지도",
  "544": "교관의 지도",
  "545": "Unavailable",
  "546": "만악룡의 패기",
  "547": "만악룡의 패기",
  "548": "Unavailable",
  "549": "자화룡의 진수",
  "550": "자화룡의 진수",
  "551": "Unavailable",
  "552": "양동 공격",
  "553": "양동 공격",
  "554": "공격을 명중시키면 몬스터의 주의를\r\n더욱 강하게 끈다.",
  "555": "공격적인 방어",
  "556": "공격적인 방어",
  "557": "타이밍을 잘 맞춰 가드에 성공하면\r\n일정 시간 공격력이 상승한다.",
  "558": "전화위복",
  "559": "전화위복",
  "560": "상태 이상 및 속성 피해에서 벗어나면\r\n일정 시간 공격 성능이 강화된다.",
  "561": "낙법술",
  "562": "낙법술",
  "563": "발도 중 공격을 받아 크게\r\n날려질 때 낙법을 취해\r\n빠르게 복귀할 수 있게 된다.",
  "564": "빙아룡의 비기",
  "565": "빙아룡의 비기",
  "566": "Unavailable",
  "567": "화룡의 진수",
  "568": "화룡의 진수",
  "569": "Unavailable",
  "570": "각룡의 패기",
  "571": "각룡의 패기",
  "572": "Unavailable",
  "573": "풍표룡의 패기",
  "574": "풍표룡의 패기",
  "575": "Unavailable",
  "576": "참조룡의 진수",
  "577": "참조룡의 진수",
  "578": "Unavailable",
  "579": "폭추룡의 패기",
  "580": "폭추룡의 패기",
  "581": "Unavailable",
  "582": "폭린룡의 패기",
  "583": "폭린룡의 패기",
  "584": "Unavailable",
  "585": "공폭룡의 진수",
  "586": "공폭룡의 진수",
  "587": "Unavailable",
  "588": "시투룡의 영맥",
  "589": "시투룡의 본보기",
  "590": "Unavailable",
  "591": "Unavailable",
  "592": "Unavailable",
  "593": "Unavailable",
  "594": "Unavailable",
  "595": "Unavailable",
  "596": "Unavailable",
  "597": "환수의 신비",
  "598": "환수의 신비",
  "599": "Unavailable",
  "600": "길드의 견식",
  "601": "길드의 품위",
  "602": "Unavailable",
  "603": "용산룡의 진수",
  "604": "용산룡의 진수",
  "605": "Unavailable",
  "606": "염비룡의 진수",
  "607": "염비룡의 진수",
  "608": "Unavailable",
  "609": "멸진룡의 패기",
  "610": "멸진룡의 패기",
  "611": "Unavailable",
  "612": "Unavailable",
  "613": "Unavailable",
  "614": "Unavailable",
  "615": "둔기 사용",
  "616": "둔기 사용",
  "617": "예리도가 나쁠수록 공격력 상승.\r\n/원거리 무기의 근접공격 위력과\r\n기절시킬 확률이 매우 크게 상승",
  "618": "분발",
  "619": "분기",
  "620": "체력이 40％ 이하가 되면 일정 시간\r\n스태미나 소비량이 감소한다.",
  "621": "추위 내성",
  "622": "추위 내성",
  "623": "추위에 의한 영향을 무효화한다.",
  "624": "금사자의 분노",
  "625": "금사자의 분노",
  "626": "Unavailable",
  "627": "동력 전지",
  "628": "동력 전지",
  "629": "Unavailable",
  "630": "서바이벌",
  "631": "서바이벌",
  "632": "Unavailable",
  "633": "명적룡의 봉인",
  "634": "명적룡의 봉인",
  "635": "Unavailable",
  "636": "만복의 축복",
  "637": "만복의 축복",
  "638": "Unavailable",
  "639": "대감사의 축복",
  "640": "대감사의 축복",
  "641": "Unavailable",
  "642": "만개의 축복",
  "643": "만개의 축복",
  "644": "Unavailable",
  "645": "Unavailable",
  "646": "Unavailable",
  "647": "Unavailable",
  "648": "Unavailable",
  "649": "Unavailable",
  "650": "Unavailable",
  "651": "금사자의 투지",
  "652": "금사자의 투지",
  "653": "Unavailable",
  "654": "쇄룡의 투지",
  "655": "쇄룡의 투지",
  "656": "Unavailable",
  "657": "난휘룡의 진수",
  "658": "난휘룡의 진수",
  "659": "Unavailable",
  "660": "Unavailable",
  "661": "Unavailable",
  "662": "Unavailable",
  "663": "Unavailable",
  "664": "Unavailable",
  "665": "Unavailable",
  "666": "Unavailable",
  "667": "Unavailable",
  "668": "Unavailable",
  "669": "Unavailable",
  "670": "Unavailable",
  "671": "Unavailable"
}