{
  "0": "クルドローンⅠ",
  "1": "クルドローンⅡ",
  "2": "クルドローンⅢ",
  "3": "アルマスタッグⅠ",
  "4": "アルマスタッグⅡ",
  "5": "アルマスタッグⅢ",
  "6": "モナークブルスタッグⅠ",
  "7": "モナークブルスタッグⅡ",
  "8": "モナークブルスタッグⅢ",
  "9": "レジナヴォランテⅠ",
  "10": "レジナヴォランテⅡ",
  "11": "レジナヴォランテⅢ",
  "12": "ガシルドーレⅠ",
  "13": "ガシルドーレⅡ",
  "14": "ガシルドーレⅢ",
  "15": "ドゥンクラープⅠ",
  "16": "ドゥンクラープⅡ",
  "17": "ドゥンクラープⅢ",
  "18": "ウカドゥーレⅠ",
  "19": "ウカドゥーレⅡ",
  "20": "ウカドゥーレⅢ",
  "21": "カゼキリバネⅠ",
  "22": "カゼキリバネⅡ",
  "23": "カゼキリバネⅢ",
  "24": "オオシナトⅠ",
  "25": "オオシナトⅡ",
  "26": "オオシナトⅢ",
  "27": "シナトモドキⅠ",
  "28": "シナトモドキⅡ",
  "29": "シナトモドキⅢ",
  "30": "マルドローンⅠ",
  "31": "マルドローンⅡ",
  "32": "マルドローンⅢ",
  "33": "ザミールビートルⅠ",
  "34": "ザミールビートルⅡ",
  "35": "ザミールビートルⅢ",
  "36": "ケーニヒゴアビートルⅠ",
  "37": "ケーニヒゴアビートルⅡ",
  "38": "ケーニヒゴアビートルⅢ",
  "39": "フィルカーノⅠ",
  "40": "フィルカーノⅡ",
  "41": "フィルカーノⅢ",
  "42": "ハルキータⅠ",
  "43": "ハルキータⅡ",
  "44": "ハルキータⅢ",
  "45": "ドルンキータⅠ",
  "46": "ドルンキータⅡ",
  "47": "ドルンキータⅢ",
  "48": "アルジョアーニャⅠ",
  "49": "アルジョアーニャⅡ",
  "50": "アルジョアーニャⅢ",
  "51": "ガルーヘルⅠ",
  "52": "ガルーヘルⅡ",
  "53": "ガルーヘルⅢ",
  "54": "メイヴァーチルⅠ",
  "55": "メイヴァーチルⅡ",
  "56": "メイヴァーチルⅢ",
  "57": "ヴァンリエールⅠ",
  "58": "ヴァンリエールⅡ",
  "59": "ヴァンリエールⅢ",
  "60": "ドラゴンソウル",
  "61": "ドラゴンソウル・真",
  "62": "サルヴァースタッグⅠ・速",
  "63": "サルヴァースタッグⅡ・速",
  "64": "サルヴァースタッグⅢ・速",
  "65": "サルヴァースタッグⅠ・攻",
  "66": "サルヴァースタッグⅡ・攻",
  "67": "サルヴァースタッグⅢ・攻",
  "68": "オスパーダドゥーレⅠ・速",
  "69": "オスパーダドゥーレⅡ・速",
  "70": "オスパーダドゥーレⅢ・速",
  "71": "オスパーダドゥーレⅠ・攻",
  "72": "オスパーダドゥーレⅡ・攻",
  "73": "オスパーダドゥーレⅢ・攻",
  "74": "シナトオオモミジⅠ・癒",
  "75": "シナトオオモミジⅡ・癒",
  "76": "シナトオオモミジⅢ・癒",
  "77": "シナトオオモミジⅠ・攻",
  "78": "シナトオオモミジⅡ・攻",
  "79": "シナトオオモミジⅢ・攻",
  "80": "エルドラーンⅠ",
  "81": "エルドラーンⅡ",
  "82": "エルドラーンⅢ",
  "83": "グランツビートルⅠ・速",
  "84": "グランツビートルⅡ・速",
  "85": "グランツビートルⅢ・速",
  "86": "グランツビートルⅠ・癒",
  "87": "グランツビートルⅡ・癒",
  "88": "グランツビートルⅢ・癒",
  "89": "アムルマリキータⅠ・攻",
  "90": "アムルマリキータⅡ・攻",
  "91": "アムルマリキータⅢ・攻",
  "92": "アムルマリキータⅠ・速",
  "93": "アムルマリキータⅡ・速",
  "94": "アムルマリキータⅢ・速",
  "95": "ヴァルフリューゲルⅠ・攻",
  "96": "ヴァルフリューゲルⅡ・攻",
  "97": "ヴァルフリューゲルⅢ・攻",
  "98": "ヴァルフリューゲルⅠ・癒",
  "99": "ヴァルフリューゲルⅡ・癒",
  "100": "ヴァルフリューゲルⅢ・癒",
  "101": "アルジャーロンⅠ",
  "102": "アルジャーロンⅡ",
  "103": "アルジャーロンⅢ",
  "104": "ドラゴンソウル・極"
}