{
  "0": "은신 복장",
  "1": "일정 시간, 몬스터의 시야에서\r\n몸을 숨긴다.\r\n공격을 받거나 데미지를 입으면\r\n효과가 종료된다.",
  "2": "Unavailable",
  "3": "은신 복장+",
  "4": "피신 복장",
  "5": "위력이 높은 공격을 받았을 때\r\n데미지를 무효화하고 자동으로\r\n회피 행동을 한다.",
  "6": "Unavailable",
  "7": "피신 복장+",
  "8": "치유의 연통",
  "9": "연통을 설치해서 플레이어의\r\n체력을 서서히 회복시키는\r\n연기를 피운다.",
  "10": "Unavailable",
  "11": "치유의 연통+",
  "12": "부동 복장",
  "13": "데미지 리액션이 없어지고\r\n풍압 무효, 청각 보호, 내진의\r\n효과를 얻는다.\r\n받는 데미지가 감소한다.",
  "14": "Unavailable",
  "15": "부동 복장+",
  "16": "도발 복장",
  "17": "몬스터에게 노려지기 쉬워지고,\r\n몬스터를 원하는 장소로 불러낸다.\r\n공격을 계속 맞히거나, 받으면\r\n효과가 종료된다.",
  "18": "Unavailable",
  "19": "도발 복장+",
  "20": "체력 복장",
  "21": "일정량의 데미지를 흡수한다.\r\n흡수량의 한계를 넘으면, 효과가\r\n종료된다.",
  "22": "Unavailable",
  "23": "체력 복장+",
  "24": "내열 복장",
  "25": "불속성의 데미지를 경감시킨다.\r\n또한, 불속성 피해나 폭파 피해,\r\n뜨거운 지형의 데미지를 \r\n무효화한다.",
  "26": "Unavailable",
  "27": "내열 복장+",
  "28": "내수 복장",
  "29": "물속성 데미지를 경감시킨다.\r\n물속성 피해나 깊은 물가에서의\r\n행동 제한을 무효화하고\r\n진흙에서의 행동 제한도 경감한다.",
  "30": "Unavailable",
  "31": "내수 복장+",
  "32": "내한 복장",
  "33": "얼음속성 데미지를 경감한다.\r\n얼음속성 피해를 무효화한다.",
  "34": "Unavailable",
  "35": "내한 복장+",
  "36": "내뢰 복장",
  "37": "번개속성 데미지를 경감한다.\r\n번개속성 피해와 마비를\r\n무효화한다.",
  "38": "Unavailable",
  "39": "내뢰 복장+",
  "40": "내룡 복장",
  "41": "용속성 데미지를 경감한다.\r\n용속성 피해를 무효화하고,\r\n무기가 가진 용속성을 강화한다.",
  "42": "Unavailable",
  "43": "내룡 복장+",
  "44": "해제의 연통",
  "45": "연통을 설치해서\r\n모든 상태 이상 및 속성 피해를\r\n회복하는 연기를 피운다.",
  "46": "Unavailable",
  "47": "해제의 연통+",
  "48": "활공 복장",
  "49": "점프의 체공 시간이 길어진다.\r\n강풍이 부는 장소에선 바람을 타고\r\n이동할 수 있다. 또 점프 공격으로\r\n몬스터에 타기가 쉬워진다.",
  "50": "Unavailable",
  "51": "활공 복장+",
  "52": "회피 복장",
  "53": "회피 중 무적 시간이 길어진다.\r\n몬스터의 공격을 직전에 회피하면,\r\n일시적으로 공격력이 올라간다.",
  "54": "Unavailable",
  "55": "회피 복장+",
  "56": "강타 복장",
  "57": "대부분의 공격에 기절치를 추가\r\n한다. 또, 이미 기절치가 있는\r\n공격이면 그 효과를 올린다.",
  "58": "Unavailable",
  "59": "강타 복장+",
  "60": "화합 복장",
  "61": "상태 이상 속성을 가진 무기로 \r\n공격 성공 시 속성치를 주는\r\n공격의 발동 확률이 올라간다.",
  "62": "Unavailable",
  "63": "화합 복장+",
  "64": "면역 복장",
  "65": "모든 상태 이상 및 속성 피해를\r\n회복하고, 효과 중에는 상태 이상 및\r\n속성 피해에 걸리지 않게 된다.",
  "66": "Unavailable",
  "67": "면역 복장+",
  "68": "달인의 연통",
  "69": "연통을 설치해서 플레이어의 \r\n회심률을 올리는 연기를 피운다.",
  "70": "Unavailable",
  "71": "달인의 연통+",
  "72": "강도 복장",
  "73": "대형 몬스터를 공격해서\r\n환금성이 높은 아이템을\r\n떨어뜨리게 할 수 있다.",
  "74": "Unavailable",
  "75": "강도 복장+",
  "76": "어쌔신 복장",
  "77": "일부 이동이 빨라지고, 기척을\r\n재빨리 감추는 어쌔신 의상.\r\n눈치 채지 못한 몬스터를 공격하면\r\n큰 데미지를 주고, 효과가 끝난다.",
  "78": "Unavailable",
  "79": "어쌔신 복장+"
}